Workbook

Sheet Dashboard
B1: VIDEO GAME INDUSTRY DASHBOARD
B3: Global sales in millions of units | 1980-2016 | Source: Video_Games_Sales_as_at_22_Dec_2016 (cleaned)
B4: GENRE | D4: PLATFORM MAKER | F4: YEAR FROM | H4: YEAR TO | J4: Pick values in the yellow cells (dropdowns). Every KPI and chart updates. Set all back to "All" / 1980-2016 to reset.
B5: All | D5: All | F5: 1980 | H5: 2016
B7: TOTAL RELEASES | D7: TOTAL SALES (M UNITS) | F7: TOP GENRE | H7: TOP PLATFORM | J7: TOP PUBLISHER | L7: AVG SALES / RELEASE (M)
B8: =SUM(Data!$P$2:$P$16716) -> 16715 | D8: =SUMIFS(Data!$J$2:$J$16716,Data!$P$2:$P$16716,1) -> 8917.88 | F8: =IF(SUM(Calc!$C$3:$C$14)=0,"n/a",INDEX(Calc!$A$3:$A$14,MATCH(MAX(Calc!$C$3:$C$14),Calc!$C$3:$C$14,0))) -> Action | H8: =IF(Calc!$V$3=0,"n/a",Calc!$U$3) -> PS2 | J8: =IF(Calc!$AD$3=0,"n/a",Calc!$AC$3) -> Nintendo | L8: =IF(B8=0,0,D8/B8) -> 0.53352558
B9: ="game releases (title x platform)" -> game releases (title x platform) | D9: =IFERROR(TEXT(D8/SUM(Data!$J$2:$J$16716),"0.0%")&" of all-time market","") -> 100.0% of all-time market | F9: =IFERROR(TEXT(MAX(Calc!$C$3:$C$14)/D8,"0.0%")&" of selected sales","") -> 19.6% of selected sales | H9: =IFERROR(TEXT(Calc!$V$3/D8,"0.0%")&" of selected sales","") -> 14.1% of selected sales | J9: =IFERROR(TEXT(Calc!$AD$3/D8,"0.0%")&" of selected sales","") -> 20.1% of selected sales | L9: ="mean units per release" -> mean units per release
B65: Note: critic-band chart covers only games that have a Metacritic score (~49%). Digital/mobile sales are not included in the source data; 2016 is a partial year.

Sheet Data
A1: Name | B1: Platform | C1: Year | D1: Genre | E1: Publisher | F1: NA_Sales | G1: EU_Sales | H1: JP_Sales | I1: Other_Sales | J1: Global_Sales | K1: Critic_Score | L1: User_Score | M1: Rating | N1: Platform_Maker | O1: Critic_Band | P1: InFilter | Q1: RankVal
A2: Wii Sports | B2: Wii | C2: 2006 | D2: Sports | E2: Nintendo | F2: 41.36 | G2: 28.96 | H2: 3.77 | I2: 8.45 | J2: 82.53 | K2: 76 | L2: 8 | M2: E | N2: Nintendo | O2: 70-79 | P2: =IF(AND(OR(Dashboard!$B$5="All",D2=Dashboard!$B$5),OR(Dashboard!$D$5="All",N2=Dashboard!$D$5),OR(AND(C2<>"",C2>=Dashboard!$F$5,C2<=Dashboard!$H$5),AND(C2="",Dashboard!$F$5<=1980,Dashboard!$H$5>=2016))),1,0) -> 1 | Q2: =J2*P2+ROW()*0.00000001 -> 82.53
A3: Super Mario Bros. | B3: NES | C3: 1985 | D3: Platform | E3: Nintendo | F3: 29.08 | G3: 3.58 | H3: 6.81 | I3: 0.77 | J3: 40.24 | N3: Nintendo | P3: =IF(AND(OR(Dashboard!$B$5="All",D3=Dashboard!$B$5),OR(Dashboard!$D$5="All",N3=Dashboard!$D$5),OR(AND(C3<>"",C3>=Dashboard!$F$5,C3<=Dashboard!$H$5),AND(C3="",Dashboard!$F$5<=1980,Dashboard!$H$5>=2016))),1,0) -> 1 | Q3: =J3*P3+ROW()*0.00000001 -> 40.24
A4: Mario Kart Wii | B4: Wii | C4: 2008 | D4: Racing | E4: Nintendo | F4: 15.68 | G4: 12.76 | H4: 3.79 | I4: 3.29 | J4: 35.52 | K4: 82 | L4: 8.3 | M4: E | N4: Nintendo | O4: 80-89 | P4: =IF(AND(OR(Dashboard!$B$5="All",D4=Dashboard!$B$5),OR(Dashboard!$D$5="All",N4=Dashboard!$D$5),OR(AND(C4<>"",C4>=Dashboard!$F$5,C4<=Dashboard!$H$5),AND(C4="",Dashboard!$F$5<=1980,Dashboard!$H$5>=2016))),1,0) -> 1 | Q4: =J4*P4+ROW()*0.00000001 -> 35.52
A5: Wii Sports Resort | B5: Wii | C5: 2009 | D5: Sports | E5: Nintendo | F5: 15.61 | G5: 10.93 | H5: 3.28 | I5: 2.95 | J5: 32.77 | K5: 80 | L5: 8 | M5: E | N5: Nintendo | O5: 70-79 | P5: =IF(AND(OR(Dashboard!$B$5="All",D5=Dashboard!$B$5),OR(Dashboard!$D$5="All",N5=Dashboard!$D$5),OR(AND(C5<>"",C5>=Dashboard!$F$5,C5<=Dashboard!$H$5),AND(C5="",Dashboard!$F$5<=1980,Dashboard!$H$5>=2016))),1,0) -> 1 | Q5: =J5*P5+ROW()*0.00000001 -> 32.77
A6: Pokemon Red/Pokemon Blue | B6: GB | C6: 1996 | D6: Role-Playing | E6: Nintendo | F6: 11.27 | G6: 8.89 | H6: 10.22 | I6: 1 | J6: 31.37 | N6: Nintendo | P6: =IF(AND(OR(Dashboard!$B$5="All",D6=Dashboard!$B$5),OR(Dashboard!$D$5="All",N6=Dashboard!$D$5),OR(AND(C6<>"",C6>=Dashboard!$F$5,C6<=Dashboard!$H$5),AND(C6="",Dashboard!$F$5<=1980,Dashboard!$H$5>=2016))),1,0) -> 1 | Q6: =J6*P6+ROW()*0.00000001 -> 31.37
A7: Tetris | B7: GB | C7: 1989 | D7: Puzzle | E7: Nintendo | F7: 23.2 | G7: 2.26 | H7: 4.22 | I7: 0.58 | J7: 30.26 | N7: Nintendo | P7: =IF(AND(OR(Dashboard!$B$5="All",D7=Dashboard!$B$5),OR(Dashboard!$D$5="All",N7=Dashboard!$D$5),OR(AND(C7<>"",C7>=Dashboard!$F$5,C7<=Dashboard!$H$5),AND(C7="",Dashboard!$F$5<=1980,Dashboard!$H$5>=2016))),1,0) -> 1 | Q7: =J7*P7+ROW()*0.00000001 -> 30.26
A8: New Super Mario Bros. | B8: DS | C8: 2006 | D8: Platform | E8: Nintendo | F8: 11.28 | G8: 9.14 | H8: 6.5 | I8: 2.88 | J8: 29.8 | K8: 89 | L8: 8.5 | M8: E | N8: Nintendo | O8: 80-89 | P8: =IF(AND(OR(Dashboard!$B$5="All",D8=Dashboard!$B$5),OR(Dashboard!$D$5="All",N8=Dashboard!$D$5),OR(AND(C8<>"",C8>=Dashboard!$F$5,C8<=Dashboard!$H$5),AND(C8="",Dashboard!$F$5<=1980,Dashboard!$H$5>=2016))),1,0) -> 1 | Q8: =J8*P8+ROW()*0.00000001 -> 29.8
A9: Wii Play | B9: Wii | C9: 2006 | D9: Misc | E9: Nintendo | F9: 13.96 | G9: 9.18 | H9: 2.93 | I9: 2.84 | J9: 28.92 | K9: 58 | L9: 6.6 | M9: E | N9: Nintendo | O9: 50-59 | P9: =IF(AND(OR(Dashboard!$B$5="All",D9=Dashboard!$B$5),OR(Dashboard!$D$5="All",N9=Dashboard!$D$5),OR(AND(C9<>"",C9>=Dashboard!$F$5,C9<=Dashboard!$H$5),AND(C9="",Dashboard!$F$5<=1980,Dashboard!$H$5>=2016))),1,0) -> 1 | Q9: =J9*P9+ROW()*0.00000001 -> 28.92
A10: New Super Mario Bros. Wii | B10: Wii | C10: 2009 | D10: Platform | E10: Nintendo | F10: 14.44 | G10: 6.94 | H10: 4.7 | I10: 2.24 | J10: 28.32 | K10: 87 | L10: 8.4 | M10: E | N10: Nintendo | O10: 80-89 | P10: =IF(AND(OR(Dashboard!$B$5="All",D10=Dashboard!$B$5),OR(Dashboard!$D$5="All",N10=Dashboard!$D$5),OR(AND(C10<>"",C10>=Dashboard!$F$5,C10<=Dashboard!$H$5),AND(C10="",Dashboard!$F$5<=1980,Dashboard!$H$5>=2016))),1,0) -> 1 | Q10: =J10*P10+ROW()*0.00000001 -> 28.32
A11: Duck Hunt | B11: NES | C11: 1984 | D11: Shooter | E11: Nintendo | F11: 26.93 | G11: 0.63 | H11: 0.28 | I11: 0.47 | J11: 28.31 | N11: Nintendo | P11: =IF(AND(OR(Dashboard!$B$5="All",D11=Dashboard!$B$5),OR(Dashboard!$D$5="All",N11=Dashboard!$D$5),OR(AND(C11<>"",C11>=Dashboard!$F$5,C11<=Dashboard!$H$5),AND(C11="",Dashboard!$F$5<=1980,Dashboard!$H$5>=2016))),1,0) -> 1 | Q11: =J11*P11+ROW()*0.00000001 -> 28.31
A12: Nintendogs | B12: DS | C12: 2005 | D12: Simulation | E12: Nintendo | F12: 9.05 | G12: 10.95 | H12: 1.93 | I12: 2.74 | J12: 24.67 | N12: Nintendo | P12: =IF(AND(OR(Dashboard!$B$5="All",D12=Dashboard!$B$5),OR(Dashboard!$D$5="All",N12=Dashboard!$D$5),OR(AND(C12<>"",C12>=Dashboard!$F$5,C12<=Dashboard!$H$5),AND(C12="",Dashboard!$F$5<=1980,Dashboard!$H$5>=2016))),1,0) -> 1 | Q12: =J12*P12+ROW()*0.00000001 -> 24.67
A13: Mario Kart DS | B13: DS | C13: 2005 | D13: Racing | E13: Nintendo | F13: 9.71 | G13: 7.47 | H13: 4.13 | I13: 1.9 | J13: 23.21 | K13: 91 | L13: 8.6 | M13: E | N13: Nintendo | O13: 90+ | P13: =IF(AND(OR(Dashboard!$B$5="All",D13=Dashboard!$B$5),OR(Dashboard!$D$5="All",N13=Dashboard!$D$5),OR(AND(C13<>"",C13>=Dashboard!$F$5,C13<=Dashboard!$H$5),AND(C13="",Dashboard!$F$5<=1980,Dashboard!$H$5>=2016))),1,0) -> 1 | Q13: =J13*P13+ROW()*0.00000001 -> 23.21
A14: Pokemon Gold/Pokemon Silver | B14: GB | C14: 1999 | D14: Role-Playing | E14: Nintendo | F14: 9 | G14: 6.18 | H14: 7.2 | I14: 0.71 | J14: 23.1 | N14: Nintendo | P14: =IF(AND(OR(Dashboard!$B$5="All",D14=Dashboard!$B$5),OR(Dashboard!$D$5="All",N14=Dashboard!$D$5),OR(AND(C14<>"",C14>=Dashboard!$F$5,C14<=Dashboard!$H$5),AND(C14="",Dashboard!$F$5<=1980,Dashboard!$H$5>=2016))),1,0) -> 1 | Q14: =J14*P14+ROW()*0.00000001 -> 23.1
A15: Wii Fit | B15: Wii | C15: 2007 | D15: Sports | E15: Nintendo | F15: 8.92 | G15: 8.03 | H15: 3.6 | I15: 2.15 | J15: 22.7 | K15: 80 | L15: 7.7 | M15: E | N15: Nintendo | O15: 70-79 | P15: =IF(AND(OR(Dashboard!$B$5="All",D15=Dashboard!$B$5),OR(Dashboard!$D$5="All",N15=Dashboard!$D$5),OR(AND(C15<>"",C15>=Dashboard!$F$5,C15<=Dashboard!$H$5),AND(C15="",Dashboard!$F$5<=1980,Dashboard!$H$5>=2016))),1,0) -> 1 | Q15: =J15*P15+ROW()*0.00000001 -> 22.7
A16: Kinect Adventures! | B16: X360 | C16: 2010 | D16: Misc | E16: Microsoft Game Studios | F16: 15 | G16: 4.89 | H16: 0.24 | I16: 1.69 | J16: 21.81 | K16: 61 | L16: 6.3 | M16: E | N16: Microsoft | O16: 60-69 | P16: =IF(AND(OR(Dashboard!$B$5="All",D16=Dashboard!$B$5),OR(Dashboard!$D$5="All",N16=Dashboard!$D$5),OR(AND(C16<>"",C16>=Dashboard!$F$5,C16<=Dashboard!$H$5),AND(C16="",Dashboard!$F$5<=1980,Dashboard!$H$5>=2016))),1,0) -> 1 | Q16: =J16*P16+ROW()*0.00000001 -> 21.81
A17: Wii Fit Plus | B17: Wii | C17: 2009 | D17: Sports | E17: Nintendo | F17: 9.01 | G17: 8.49 | H17: 2.53 | I17: 1.77 | J17: 21.79 | K17: 80 | L17: 7.4 | M17: E | N17: Nintendo | O17: 70-79 | P17: =IF(AND(OR(Dashboard!$B$5="All",D17=Dashboard!$B$5),OR(Dashboard!$D$5="All",N17=Dashboard!$D$5),OR(AND(C17<>"",C17>=Dashboard!$F$5,C17<=Dashboard!$H$5),AND(C17="",Dashboard!$F$5<=1980,Dashboard!$H$5>=2016))),1,0) -> 1 | Q17: =J17*P17+ROW()*0.00000001 -> 21.79
A18: Grand Theft Auto V | B18: PS3 | C18: 2013 | D18: Action | E18: Take-Two Interactive | F18: 7.02 | G18: 9.09 | H18: 0.98 | I18: 3.96 | J18: 21.04 | K18: 97 | L18: 8.2 | M18: M | N18: Sony | O18: 90+ | P18: =IF(AND(OR(Dashboard!$B$5="All",D18=Dashboard!$B$5),OR(Dashboard!$D$5="All",N18=Dashboard!$D$5),OR(AND(C18<>"",C18>=Dashboard!$F$5,C18<=Dashboard!$H$5),AND(C18="",Dashboard!$F$5<=1980,Dashboard!$H$5>=2016))),1,0) -> 1 | Q18: =J18*P18+ROW()*0.00000001 -> 21.04
A19: Grand Theft Auto: San Andreas | B19: PS2 | C19: 2004 | D19: Action | E19: Take-Two Interactive | F19: 9.43 | G19: 0.4 | H19: 0.41 | I19: 10.57 | J19: 20.81 | K19: 95 | L19: 9 | M19: M | N19: Sony | O19: 90+ | P19: =IF(AND(OR(Dashboard!$B$5="All",D19=Dashboard!$B$5),OR(Dashboard!$D$5="All",N19=Dashboard!$D$5),OR(AND(C19<>"",C19>=Dashboard!$F$5,C19<=Dashboard!$H$5),AND(C19="",Dashboard!$F$5<=1980,Dashboard!$H$5>=2016))),1,0) -> 1 | Q19: =J19*P19+ROW()*0.00000001 -> 20.81
A20: Super Mario World | B20: SNES | C20: 1990 | D20: Platform | E20: Nintendo | F20: 12.78 | G20: 3.75 | H20: 3.54 | I20: 0.55 | J20: 20.61 | N20: Nintendo | P20: =IF(AND(OR(Dashboard!$B$5="All",D20=Dashboard!$B$5),OR(Dashboard!$D$5="All",N20=Dashboard!$D$5),OR(AND(C20<>"",C20>=Dashboard!$F$5,C20<=Dashboard!$H$5),AND(C20="",Dashboard!$F$5<=1980,Dashboard!$H$5>=2016))),1,0) -> 1 | Q20: =J20*P20+ROW()*0.00000001 -> 20.61
A21: Brain Age: Train Your Brain in Minutes a Day | B21: DS | C21: 2005 | D21: Misc | E21: Nintendo | F21: 4.74 | G21: 9.2 | H21: 4.16 | I21: 2.04 | J21: 20.15 | K21: 77 | L21: 7.9 | M21: E | N21: Nintendo | O21: 70-79 | P21: =IF(AND(OR(Dashboard!$B$5="All",D21=Dashboard!$B$5),OR(Dashboard!$D$5="All",N21=Dashboard!$D$5),OR(AND(C21<>"",C21>=Dashboard!$F$5,C21<=Dashboard!$H$5),AND(C21="",Dashboard!$F$5<=1980,Dashboard!$H$5>=2016))),1,0) -> 1 | Q21: =J21*P21+ROW()*0.00000001 -> 20.15
A22: Pokemon Diamond/Pokemon Pearl | B22: DS | C22: 2006 | D22: Role-Playing | E22: Nintendo | F22: 6.38 | G22: 4.46 | H22: 6.04 | I22: 1.36 | J22: 18.25 | N22: Nintendo | P22: =IF(AND(OR(Dashboard!$B$5="All",D22=Dashboard!$B$5),OR(Dashboard!$D$5="All",N22=Dashboard!$D$5),OR(AND(C22<>"",C22>=Dashboard!$F$5,C22<=Dashboard!$H$5),AND(C22="",Dashboard!$F$5<=1980,Dashboard!$H$5>=2016))),1,0) -> 1 | Q22: =J22*P22+ROW()*0.00000001 -> 18.25
A23: Super Mario Land | B23: GB | C23: 1989 | D23: Platform | E23: Nintendo | F23: 10.83 | G23: 2.71 | H23: 4.18 | I23: 0.42 | J23: 18.14 | N23: Nintendo | P23: =IF(AND(OR(Dashboard!$B$5="All",D23=Dashboard!$B$5),OR(Dashboard!$D$5="All",N23=Dashboard!$D$5),OR(AND(C23<>"",C23>=Dashboard!$F$5,C23<=Dashboard!$H$5),AND(C23="",Dashboard!$F$5<=1980,Dashboard!$H$5>=2016))),1,0) -> 1 | Q23: =J23*P23+ROW()*0.00000001 -> 18.14
A24: Super Mario Bros. 3 | B24: NES | C24: 1988 | D24: Platform | E24: Nintendo | F24: 9.54 | G24: 3.44 | H24: 3.84 | I24: 0.46 | J24: 17.28 | N24: Nintendo | P24: =IF(AND(OR(Dashboard!$B$5="All",D24=Dashboard!$B$5),OR(Dashboard!$D$5="All",N24=Dashboard!$D$5),OR(AND(C24<>"",C24>=Dashboard!$F$5,C24<=Dashboard!$H$5),AND(C24="",Dashboard!$F$5<=1980,Dashboard!$H$5>=2016))),1,0) -> 1 | Q24: =J24*P24+ROW()*0.00000001 -> 17.28
A25: Grand Theft Auto V | B25: X360 | C25: 2013 | D25: Action | E25: Take-Two Interactive | F25: 9.66 | G25: 5.14 | H25: 0.06 | I25: 1.41 | J25: 16.27 | K25: 97 | L25: 8.1 | M25: M | N25: Microsoft | O25: 90+ | P25: =IF(AND(OR(Dashboard!$B$5="All",D25=Dashboard!$B$5),OR(Dashboard!$D$5="All",N25=Dashboard!$D$5),OR(AND(C25<>"",C25>=Dashboard!$F$5,C25<=Dashboard!$H$5),AND(C25="",Dashboard!$F$5<=1980,Dashboard!$H$5>=2016))),1,0) -> 1 | Q25: =J25*P25+ROW()*0.00000001 -> 16.27
A26: Grand Theft Auto: Vice City | B26: PS2 | C26: 2002 | D26: Action | E26: Take-Two Interactive | F26: 8.41 | G26: 5.49 | H26: 0.47 | I26: 1.78 | J26: 16.15 | K26: 95 | L26: 8.7 | M26: M | N26: Sony | O26: 90+ | P26: =IF(AND(OR(Dashboard!$B$5="All",D26=Dashboard!$B$5),OR(Dashboard!$D$5="All",N26=Dashboard!$D$5),OR(AND(C26<>"",C26>=Dashboard!$F$5,C26<=Dashboard!$H$5),AND(C26="",Dashboard!$F$5<=1980,Dashboard!$H$5>=2016))),1,0) -> 1 | Q26: =J26*P26+ROW()*0.00000001 -> 16.15
A27: Pokemon Ruby/Pokemon Sapphire | B27: GBA | C27: 2002 | D27: Role-Playing | E27: Nintendo | F27: 6.06 | G27: 3.9 | H27: 5.38 | I27: 0.5 | J27: 15.85 | N27: Nintendo | P27: =IF(AND(OR(Dashboard!$B$5="All",D27=Dashboard!$B$5),OR(Dashboard!$D$5="All",N27=Dashboard!$D$5),OR(AND(C27<>"",C27>=Dashboard!$F$5,C27<=Dashboard!$H$5),AND(C27="",Dashboard!$F$5<=1980,Dashboard!$H$5>=2016))),1,0) -> 1 | Q27: =J27*P27+ROW()*0.00000001 -> 15.85
A28: Brain Age 2: More Training in Minutes a Day | B28: DS | C28: 2005 | D28: Puzzle | E28: Nintendo | F28: 3.43 | G28: 5.35 | H28: 5.32 | I28: 1.18 | J28: 15.29 | K28: 77 | L28: 7.1 | M28: E | N28: Nintendo | O28: 70-79 | P28: =IF(AND(OR(Dashboard!$B$5="All",D28=Dashboard!$B$5),OR(Dashboard!$D$5="All",N28=Dashboard!$D$5),OR(AND(C28<>"",C28>=Dashboard!$F$5,C28<=Dashboard!$H$5),AND(C28="",Dashboard!$F$5<=1980,Dashboard!$H$5>=2016))),1,0) -> 1 | Q28: =J28*P28+ROW()*0.00000001 -> 15.29
A29: Pokemon Black/Pokemon White | B29: DS | C29: 2010 | D29: Role-Playing | E29: Nintendo | F29: 5.51 | G29: 3.17 | H29: 5.65 | I29: 0.8 | J29: 15.14 | N29: Nintendo | P29: =IF(AND(OR(Dashboard!$B$5="All",D29=Dashboard!$B$5),OR(Dashboard!$D$5="All",N29=Dashboard!$D$5),OR(AND(C29<>"",C29>=Dashboard!$F$5,C29<=Dashboard!$H$5),AND(C29="",Dashboard!$F$5<=1980,Dashboard!$H$5>=2016))),1,0) -> 1 | Q29: =J29*P29+ROW()*0.00000001 -> 15.14
A30: Gran Turismo 3: A-Spec | B30: PS2 | C30: 2001 | D30: Racing | E30: Sony Computer Entertainment | F30: 6.85 | G30: 5.09 | H30: 1.87 | I30: 1.16 | J30: 14.98 | K30: 95 | L30: 8.4 | M30: E | N30: Sony | O30: 90+ | P30: =IF(AND(OR(Dashboard!$B$5="All",D30=Dashboard!$B$5),OR(Dashboard!$D$5="All",N30=Dashboard!$D$5),OR(AND(C30<>"",C30>=Dashboard!$F$5,C30<=Dashboard!$H$5),AND(C30="",Dashboard!$F$5<=1980,Dashboard!$H$5>=2016))),1,0) -> 1 | Q30: =J30*P30+ROW()*0.00000001 -> 14.98
A31: Call of Duty: Modern Warfare 3 | B31: X360 | C31: 2011 | D31: Shooter | E31: Activision | F31: 9.04 | G31: 4.24 | H31: 0.13 | I31: 1.32 | J31: 14.73 | K31: 88 | L31: 3.4 | M31: M | N31: Microsoft | O31: 80-89 | P31: =IF(AND(OR(Dashboard!$B$5="All",D31=Dashboard!$B$5),OR(Dashboard!$D$5="All",N31=Dashboard!$D$5),OR(AND(C31<>"",C31>=Dashboard!$F$5,C31<=Dashboard!$H$5),AND(C31="",Dashboard!$F$5<=1980,Dashboard!$H$5>=2016))),1,0) -> 1 | Q31: =J31*P31+ROW()*0.00000001 -> 14.73
A32: Pokémon Yellow: Special Pikachu Edition | B32: GB | C32: 1998 | D32: Role-Playing | E32: Nintendo | F32: 5.89 | G32: 5.04 | H32: 3.12 | I32: 0.59 | J32: 14.64 | N32: Nintendo | P32: =IF(AND(OR(Dashboard!$B$5="All",D32=Dashboard!$B$5),OR(Dashboard!$D$5="All",N32=Dashboard!$D$5),OR(AND(C32<>"",C32>=Dashboard!$F$5,C32<=Dashboard!$H$5),AND(C32="",Dashboard!$F$5<=1980,Dashboard!$H$5>=2016))),1,0) -> 1 | Q32: =J32*P32+ROW()*0.00000001 -> 14.64
A33: Call of Duty: Black Ops 3 | B33: PS4 | C33: 2015 | D33: Shooter | E33: Activision | F33: 6.03 | G33: 5.86 | H33: 0.36 | I33: 2.38 | J33: 14.63 | N33: Sony | P33: =IF(AND(OR(Dashboard!$B$5="All",D33=Dashboard!$B$5),OR(Dashboard!$D$5="All",N33=Dashboard!$D$5),OR(AND(C33<>"",C33>=Dashboard!$F$5,C33<=Dashboard!$H$5),AND(C33="",Dashboard!$F$5<=1980,Dashboard!$H$5>=2016))),1,0) -> 1 | Q33: =J33*P33+ROW()*0.00000001 -> 14.63
A34: Call of Duty: Black Ops | B34: X360 | C34: 2010 | D34: Shooter | E34: Activision | F34: 9.7 | G34: 3.68 | H34: 0.11 | I34: 1.13 | J34: 14.61 | K34: 87 | L34: 6.3 | M34: M | N34: Microsoft | O34: 80-89 | P34: =IF(AND(OR(Dashboard!$B$5="All",D34=Dashboard!$B$5),OR(Dashboard!$D$5="All",N34=Dashboard!$D$5),OR(AND(C34<>"",C34>=Dashboard!$F$5,C34<=Dashboard!$H$5),AND(C34="",Dashboard!$F$5<=1980,Dashboard!$H$5>=2016))),1,0) -> 1 | Q34: =J34*P34+ROW()*0.00000001 -> 14.61
A35: Pokemon X/Pokemon Y | B35: 3DS | C35: 2013 | D35: Role-Playing | E35: Nintendo | F35: 5.28 | G35: 4.19 | H35: 4.35 | I35: 0.78 | J35: 14.6 | N35: Nintendo | P35: =IF(AND(OR(Dashboard!$B$5="All",D35=Dashboard!$B$5),OR(Dashboard!$D$5="All",N35=Dashboard!$D$5),OR(AND(C35<>"",C35>=Dashboard!$F$5,C35<=Dashboard!$H$5),AND(C35="",Dashboard!$F$5<=1980,Dashboard!$H$5>=2016))),1,0) -> 1 | Q35: =J35*P35+ROW()*0.00000001 -> 14.6
A36: Call of Duty: Black Ops II | B36: PS3 | C36: 2012 | D36: Shooter | E36: Activision | F36: 4.99 | G36: 5.73 | H36: 0.65 | I36: 2.42 | J36: 13.79 | K36: 83 | L36: 5.3 | M36: M | N36: Sony | O36: 80-89 | P36: =IF(AND(OR(Dashboard!$B$5="All",D36=Dashboard!$B$5),OR(Dashboard!$D$5="All",N36=Dashboard!$D$5),OR(AND(C36<>"",C36>=Dashboard!$F$5,C36<=Dashboard!$H$5),AND(C36="",Dashboard!$F$5<=1980,Dashboard!$H$5>=2016))),1,0) -> 1 | Q36: =J36*P36+ROW()*0.00000001 -> 13.79
A37: Call of Duty: Black Ops II | B37: X360 | C37: 2012 | D37: Shooter | E37: Activision | F37: 8.25 | G37: 4.24 | H37: 0.07 | I37: 1.12 | J37: 13.67 | K37: 83 | L37: 4.8 | M37: M | N37: Microsoft | O37: 80-89 | P37: =IF(AND(OR(Dashboard!$B$5="All",D37=Dashboard!$B$5),OR(Dashboard!$D$5="All",N37=Dashboard!$D$5),OR(AND(C37<>"",C37>=Dashboard!$F$5,C37<=Dashboard!$H$5),AND(C37="",Dashboard!$F$5<=1980,Dashboard!$H$5>=2016))),1,0) -> 1 | Q37: =J37*P37+ROW()*0.00000001 -> 13.67
A38: Call of Duty: Modern Warfare 2 | B38: X360 | C38: 2009 | D38: Shooter | E38: Activision | F38: 8.52 | G38: 3.59 | H38: 0.08 | I38: 1.28 | J38: 13.47 | K38: 94 | L38: 6.3 | M38: M | N38: Microsoft | O38: 90+ | P38: =IF(AND(OR(Dashboard!$B$5="All",D38=Dashboard!$B$5),OR(Dashboard!$D$5="All",N38=Dashboard!$D$5),OR(AND(C38<>"",C38>=Dashboard!$F$5,C38<=Dashboard!$H$5),AND(C38="",Dashboard!$F$5<=1980,Dashboard!$H$5>=2016))),1,0) -> 1 | Q38: =J38*P38+ROW()*0.00000001 -> 13.47
A39: Call of Duty: Modern Warfare 3 | B39: PS3 | C39: 2011 | D39: Shooter | E39: Activision | F39: 5.54 | G39: 5.73 | H39: 0.49 | I39: 1.57 | J39: 13.32 | K39: 88 | L39: 3.2 | M39: M | N39: Sony | O39: 80-89 | P39: =IF(AND(OR(Dashboard!$B$5="All",D39=Dashboard!$B$5),OR(Dashboard!$D$5="All",N39=Dashboard!$D$5),OR(AND(C39<>"",C39>=Dashboard!$F$5,C39<=Dashboard!$H$5),AND(C39="",Dashboard!$F$5<=1980,Dashboard!$H$5>=2016))),1,0) -> 1 | Q39: =J39*P39+ROW()*0.00000001 -> 13.32
A40: Grand Theft Auto III | B40: PS2 | C40: 2001 | D40: Action | E40: Take-Two Interactive | F40: 6.99 | G40: 4.51 | H40: 0.3 | I40: 1.3 | J40: 13.1 | K40: 97 | L40: 8.5 | M40: M | N40: Sony | O40: 90+ | P40: =IF(AND(OR(Dashboard!$B$5="All",D40=Dashboard!$B$5),OR(Dashboard!$D$5="All",N40=Dashboard!$D$5),OR(AND(C40<>"",C40>=Dashboard!$F$5,C40<=Dashboard!$H$5),AND(C40="",Dashboard!$F$5<=1980,Dashboard!$H$5>=2016))),1,0) -> 1 | Q40: =J40*P40+ROW()*0.00000001 -> 13.1
A41: Super Smash Bros. Brawl | B41: Wii | C41: 2008 | D41: Fighting | E41: Nintendo | F41: 6.62 | G41: 2.55 | H41: 2.66 | I41: 1.01 | J41: 12.84 | K41: 93 | L41: 8.9 | M41: T | N41: Nintendo | O41: 90+ | P41: =IF(AND(OR(Dashboard!$B$5="All",D41=Dashboard!$B$5),OR(Dashboard!$D$5="All",N41=Dashboard!$D$5),OR(AND(C41<>"",C41>=Dashboard!$F$5,C41<=Dashboard!$H$5),AND(C41="",Dashboard!$F$5<=1980,Dashboard!$H$5>=2016))),1,0) -> 1 | Q41: =J41*P41+ROW()*0.00000001 -> 12.84
A42: Mario Kart 7 | B42: 3DS | C42: 2011 | D42: Racing | E42: Nintendo | F42: 5.03 | G42: 4.02 | H42: 2.69 | I42: 0.91 | J42: 12.66 | K42: 85 | L42: 8.2 | M42: E | N42: Nintendo | O42: 80-89 | P42: =IF(AND(OR(Dashboard!$B$5="All",D42=Dashboard!$B$5),OR(Dashboard!$D$5="All",N42=Dashboard!$D$5),OR(AND(C42<>"",C42>=Dashboard!$F$5,C42<=Dashboard!$H$5),AND(C42="",Dashboard!$F$5<=1980,Dashboard!$H$5>=2016))),1,0) -> 1 | Q42: =J42*P42+ROW()*0.00000001 -> 12.66
A43: Call of Duty: Black Ops | B43: PS3 | C43: 2010 | D43: Shooter | E43: Activision | F43: 5.99 | G43: 4.37 | H43: 0.48 | I43: 1.79 | J43: 12.63 | K43: 88 | L43: 6.4 | M43: M | N43: Sony | O43: 80-89 | P43: =IF(AND(OR(Dashboard!$B$5="All",D43=Dashboard!$B$5),OR(Dashboard!$D$5="All",N43=Dashboard!$D$5),OR(AND(C43<>"",C43>=Dashboard!$F$5,C43<=Dashboard!$H$5),AND(C43="",Dashboard!$F$5<=1980,Dashboard!$H$5>=2016))),1,0) -> 1 | Q43: =J43*P43+ROW()*0.00000001 -> 12.63
A44: Grand Theft Auto V | B44: PS4 | C44: 2014 | D44: Action | E44: Take-Two Interactive | F44: 3.96 | G44: 6.31 | H44: 0.38 | I44: 1.97 | J44: 12.61 | K44: 97 | L44: 8.3 | M44: M | N44: Sony | O44: 90+ | P44: =IF(AND(OR(Dashboard!$B$5="All",D44=Dashboard!$B$5),OR(Dashboard!$D$5="All",N44=Dashboard!$D$5),OR(AND(C44<>"",C44>=Dashboard!$F$5,C44<=Dashboard!$H$5),AND(C44="",Dashboard!$F$5<=1980,Dashboard!$H$5>=2016))),1,0) -> 1 | Q44: =J44*P44+ROW()*0.00000001 -> 12.61
A45: Animal Crossing: Wild World | B45: DS | C45: 2005 | D45: Simulation | E45: Nintendo | F45: 2.5 | G45: 3.45 | H45: 5.33 | I45: 0.86 | J45: 12.13 | K45: 86 | L45: 8.7 | M45: E | N45: Nintendo | O45: 80-89 | P45: =IF(AND(OR(Dashboard!$B$5="All",D45=Dashboard!$B$5),OR(Dashboard!$D$5="All",N45=Dashboard!$D$5),OR(AND(C45<>"",C45>=Dashboard!$F$5,C45<=Dashboard!$H$5),AND(C45="",Dashboard!$F$5<=1980,Dashboard!$H$5>=2016))),1,0) -> 1 | Q45: =J45*P45+ROW()*0.00000001 -> 12.13
A46: Halo 3 | B46: X360 | C46: 2007 | D46: Shooter | E46: Microsoft Game Studios | F46: 7.97 | G46: 2.81 | H46: 0.13 | I46: 1.21 | J46: 12.12 | K46: 94 | L46: 7.8 | M46: M | N46: Microsoft | O46: 90+ | P46: =IF(AND(OR(Dashboard!$B$5="All",D46=Dashboard!$B$5),OR(Dashboard!$D$5="All",N46=Dashboard!$D$5),OR(AND(C46<>"",C46>=Dashboard!$F$5,C46<=Dashboard!$H$5),AND(C46="",Dashboard!$F$5<=1980,Dashboard!$H$5>=2016))),1,0) -> 1 | Q46: =J46*P46+ROW()*0.00000001 -> 12.12
A47: Super Mario 64 | B47: N64 | C47: 1996 | D47: Platform | E47: Nintendo | F47: 6.91 | G47: 2.85 | H47: 1.91 | I47: 0.23 | J47: 11.89 | N47: Nintendo | P47: =IF(AND(OR(Dashboard!$B$5="All",D47=Dashboard!$B$5),OR(Dashboard!$D$5="All",N47=Dashboard!$D$5),OR(AND(C47<>"",C47>=Dashboard!$F$5,C47<=Dashboard!$H$5),AND(C47="",Dashboard!$F$5<=1980,Dashboard!$H$5>=2016))),1,0) -> 1 | Q47: =J47*P47+ROW()*0.00000001 -> 11.89
A48: Pokemon HeartGold/Pokemon SoulSilver | B48: DS | C48: 2009 | D48: Action | E48: Nintendo | F48: 4.34 | G48: 2.71 | H48: 3.96 | I48: 0.76 | J48: 11.77 | N48: Nintendo | P48: =IF(AND(OR(Dashboard!$B$5="All",D48=Dashboard!$B$5),OR(Dashboard!$D$5="All",N48=Dashboard!$D$5),OR(AND(C48<>"",C48>=Dashboard!$F$5,C48<=Dashboard!$H$5),AND(C48="",Dashboard!$F$5<=1980,Dashboard!$H$5>=2016))),1,0) -> 1 | Q48: =J48*P48+ROW()*0.00000001 -> 11.77
A49: Pokemon Omega Ruby/Pokemon Alpha Sapphire | B49: 3DS | C49: 2014 | D49: Role-Playing | E49: Nintendo | F49: 4.35 | G49: 3.49 | H49: 3.1 | I49: 0.74 | J49: 11.68 | N49: Nintendo | P49: =IF(AND(OR(Dashboard!$B$5="All",D49=Dashboard!$B$5),OR(Dashboard!$D$5="All",N49=Dashboard!$D$5),OR(AND(C49<>"",C49>=Dashboard!$F$5,C49<=Dashboard!$H$5),AND(C49="",Dashboard!$F$5<=1980,Dashboard!$H$5>=2016))),1,0) -> 1 | Q49: =J49*P49+ROW()*0.00000001 -> 11.68
A50: Gran Turismo 4 | B50: PS2 | C50: 2004 | D50: Racing | E50: Sony Computer Entertainment | F50: 3.01 | G50: 0.01 | H50: 1.1 | I50: 7.53 | J50: 11.66 | K50: 89 | L50: 8.5 | M50: E | N50: Sony | O50: 80-89 | P50: =IF(AND(OR(Dashboard!$B$5="All",D50=Dashboard!$B$5),OR(Dashboard!$D$5="All",N50=Dashboard!$D$5),OR(AND(C50<>"",C50>=Dashboard!$F$5,C50<=Dashboard!$H$5),AND(C50="",Dashboard!$F$5<=1980,Dashboard!$H$5>=2016))),1,0) -> 1 | Q50: =J50*P50+ROW()*0.00000001 -> 11.660001
A51: Super Mario Galaxy | B51: Wii | C51: 2007 | D51: Platform | E51: Nintendo | F51: 6.06 | G51: 3.35 | H51: 1.2 | I51: 0.74 | J51: 11.35 | K51: 97 | L51: 8.9 | M51: E | N51: Nintendo | O51: 90+ | P51: =IF(AND(OR(Dashboard!$B$5="All",D51=Dashboard!$B$5),OR(Dashboard!$D$5="All",N51=Dashboard!$D$5),OR(AND(C51<>"",C51>=Dashboard!$F$5,C51<=Dashboard!$H$5),AND(C51="",Dashboard!$F$5<=1980,Dashboard!$H$5>=2016))),1,0) -> 1 | Q51: =J51*P51+ROW()*0.00000001 -> 11.350001
A52: Super Mario Land 2: 6 Golden Coins | B52: GB | C52: 1992 | D52: Adventure | E52: Nintendo | F52: 6.16 | G52: 2.04 | H52: 2.69 | I52: 0.29 | J52: 11.18 | N52: Nintendo | P52: =IF(AND(OR(Dashboard!$B$5="All",D52=Dashboard!$B$5),OR(Dashboard!$D$5="All",N52=Dashboard!$D$5),OR(AND(C52<>"",C52>=Dashboard!$F$5,C52<=Dashboard!$H$5),AND(C52="",Dashboard!$F$5<=1980,Dashboard!$H$5>=2016))),1,0) -> 1 | Q52: =J52*P52+ROW()*0.00000001 -> 11.180001
A53: Grand Theft Auto IV | B53: X360 | C53: 2008 | D53: Action | E53: Take-Two Interactive | F53: 6.76 | G53: 3.07 | H53: 0.14 | I53: 1.03 | J53: 11.01 | K53: 98 | L53: 7.9 | M53: M | N53: Microsoft | O53: 90+ | P53: =IF(AND(OR(Dashboard!$B$5="All",D53=Dashboard!$B$5),OR(Dashboard!$D$5="All",N53=Dashboard!$D$5),OR(AND(C53<>"",C53>=Dashboard!$F$5,C53<=Dashboard!$H$5),AND(C53="",Dashboard!$F$5<=1980,Dashboard!$H$5>=2016))),1,0) -> 1 | Q53: =J53*P53+ROW()*0.00000001 -> 11.010001
A54: Gran Turismo | B54: PS | C54: 1997 | D54: Racing | E54: Sony Computer Entertainment | F54: 4.02 | G54: 3.87 | H54: 2.54 | I54: 0.52 | J54: 10.95 | K54: 96 | L54: 8.7 | M54: E | N54: Sony | O54: 90+ | P54: =IF(AND(OR(Dashboard!$B$5="All",D54=Dashboard!$B$5),OR(Dashboard!$D$5="All",N54=Dashboard!$D$5),OR(AND(C54<>"",C54>=Dashboard!$F$5,C54<=Dashboard!$H$5),AND(C54="",Dashboard!$F$5<=1980,Dashboard!$H$5>=2016))),1,0) -> 1 | Q54: =J54*P54+ROW()*0.00000001 -> 10.950001
A55: Super Mario 3D Land | B55: 3DS | C55: 2011 | D55: Platform | E55: Nintendo | F55: 4.89 | G55: 3 | H55: 2.14 | I55: 0.78 | J55: 10.81 | K55: 90 | L55: 8.4 | M55: E | N55: Nintendo | O55: 80-89 | P55: =IF(AND(OR(Dashboard!$B$5="All",D55=Dashboard!$B$5),OR(Dashboard!$D$5="All",N55=Dashboard!$D$5),OR(AND(C55<>"",C55>=Dashboard!$F$5,C55<=Dashboard!$H$5),AND(C55="",Dashboard!$F$5<=1980,Dashboard!$H$5>=2016))),1,0) -> 1 | Q55: =J55*P55+ROW()*0.00000001 -> 10.810001
A56: Gran Turismo 5 | B56: PS3 | C56: 2010 | D56: Racing | E56: Sony Computer Entertainment | F56: 2.96 | G56: 4.82 | H56: 0.81 | I56: 2.11 | J56: 10.7 | K56: 84 | L56: 7.5 | M56: E | N56: Sony | O56: 80-89 | P56: =IF(AND(OR(Dashboard!$B$5="All",D56=Dashboard!$B$5),OR(Dashboard!$D$5="All",N56=Dashboard!$D$5),OR(AND(C56<>"",C56>=Dashboard!$F$5,C56<=Dashboard!$H$5),AND(C56="",Dashboard!$F$5<=1980,Dashboard!$H$5>=2016))),1,0) -> 1 | Q56: =J56*P56+ROW()*0.00000001 -> 10.700001
A57: Call of Duty: Modern Warfare 2 | B57: PS3 | C57: 2009 | D57: Shooter | E57: Activision | F57: 4.99 | G57: 3.64 | H57: 0.38 | I57: 1.6 | J57: 10.6 | K57: 94 | L57: 6.3 | M57: M | N57: Sony | O57: 90+ | P57: =IF(AND(OR(Dashboard!$B$5="All",D57=Dashboard!$B$5),OR(Dashboard!$D$5="All",N57=Dashboard!$D$5),OR(AND(C57<>"",C57>=Dashboard!$F$5,C57<=Dashboard!$H$5),AND(C57="",Dashboard!$F$5<=1980,Dashboard!$H$5>=2016))),1,0) -> 1 | Q57: =J57*P57+ROW()*0.00000001 -> 10.600001
A58: Super Mario All-Stars | B58: SNES | C58: 1993 | D58: Platform | E58: Nintendo | F58: 5.99 | G58: 2.15 | H58: 2.12 | I58: 0.29 | J58: 10.55 | N58: Nintendo | P58: =IF(AND(OR(Dashboard!$B$5="All",D58=Dashboard!$B$5),OR(Dashboard!$D$5="All",N58=Dashboard!$D$5),OR(AND(C58<>"",C58>=Dashboard!$F$5,C58<=Dashboard!$H$5),AND(C58="",Dashboard!$F$5<=1980,Dashboard!$H$5>=2016))),1,0) -> 1 | Q58: =J58*P58+ROW()*0.00000001 -> 10.550001
A59: Grand Theft Auto IV | B59: PS3 | C59: 2008 | D59: Action | E59: Take-Two Interactive | F59: 4.76 | G59: 3.69 | H59: 0.44 | I59: 1.61 | J59: 10.5 | K59: 98 | L59: 7.5 | M59: M | N59: Sony | O59: 90+ | P59: =IF(AND(OR(Dashboard!$B$5="All",D59=Dashboard!$B$5),OR(Dashboard!$D$5="All",N59=Dashboard!$D$5),OR(AND(C59<>"",C59>=Dashboard!$F$5,C59<=Dashboard!$H$5),AND(C59="",Dashboard!$F$5<=1980,Dashboard!$H$5>=2016))),1,0) -> 1 | Q59: =J59*P59+ROW()*0.00000001 -> 10.500001
A60: Pokemon FireRed/Pokemon LeafGreen | B60: GBA | C60: 2004 | D60: Role-Playing | E60: Nintendo | F60: 4.34 | G60: 2.65 | H60: 3.15 | I60: 0.35 | J60: 10.49 | N60: Nintendo | P60: =IF(AND(OR(Dashboard!$B$5="All",D60=Dashboard!$B$5),OR(Dashboard!$D$5="All",N60=Dashboard!$D$5),OR(AND(C60<>"",C60>=Dashboard!$F$5,C60<=Dashboard!$H$5),AND(C60="",Dashboard!$F$5<=1980,Dashboard!$H$5>=2016))),1,0) -> 1 | Q60: =J60*P60+ROW()*0.00000001 -> 10.490001
A61: Super Mario 64 | B61: DS | C61: 2004 | D61: Platform | E61: Nintendo | F61: 5.01 | G61: 3.07 | H61: 1.25 | I61: 0.97 | J61: 10.3 | N61: Nintendo | P61: =IF(AND(OR(Dashboard!$B$5="All",D61=Dashboard!$B$5),OR(Dashboard!$D$5="All",N61=Dashboard!$D$5),OR(AND(C61<>"",C61>=Dashboard!$F$5,C61<=Dashboard!$H$5),AND(C61="",Dashboard!$F$5<=1980,Dashboard!$H$5>=2016))),1,0) -> 1 | Q61: =J61*P61+ROW()*0.00000001 -> 10.300001
A62: Call of Duty: Ghosts | B62: X360 | C62: 2013 | D62: Shooter | E62: Activision | F62: 6.73 | G62: 2.56 | H62: 0.04 | I62: 0.91 | J62: 10.25 | K62: 73 | L62: 2.6 | M62: M | N62: Microsoft | O62: 70-79 | P62: =IF(AND(OR(Dashboard!$B$5="All",D62=Dashboard!$B$5),OR(Dashboard!$D$5="All",N62=Dashboard!$D$5),OR(AND(C62<>"",C62>=Dashboard!$F$5,C62<=Dashboard!$H$5),AND(C62="",Dashboard!$F$5<=1980,Dashboard!$H$5>=2016))),1,0) -> 1 | Q62: =J62*P62+ROW()*0.00000001 -> 10.250001
A63: Just Dance 3 | B63: Wii | C63: 2011 | D63: Misc | E63: Ubisoft | F63: 5.95 | G63: 3.11 | H63: 0 | I63: 1.06 | J63: 10.12 | K63: 74 | L63: 7.8 | M63: E10+ | N63: Nintendo | O63: 70-79 | P63: =IF(AND(OR(Dashboard!$B$5="All",D63=Dashboard!$B$5),OR(Dashboard!$D$5="All",N63=Dashboard!$D$5),OR(AND(C63<>"",C63>=Dashboard!$F$5,C63<=Dashboard!$H$5),AND(C63="",Dashboard!$F$5<=1980,Dashboard!$H$5>=2016))),1,0) -> 1 | Q63: =J63*P63+ROW()*0.00000001 -> 10.120001
A64: New Super Mario Bros. 2 | B64: 3DS | C64: 2012 | D64: Platform | E64: Nintendo | F64: 3.66 | G64: 3.14 | H64: 2.47 | I64: 0.63 | J64: 9.9 | K64: 78 | L64: 7.2 | M64: E | N64: Nintendo | O64: 70-79 | P64: =IF(AND(OR(Dashboard!$B$5="All",D64=Dashboard!$B$5),OR(Dashboard!$D$5="All",N64=Dashboard!$D$5),OR(AND(C64<>"",C64>=Dashboard!$F$5,C64<=Dashboard!$H$5),AND(C64="",Dashboard!$F$5<=1980,Dashboard!$H$5>=2016))),1,0) -> 1 | Q64: =J64*P64+ROW()*0.00000001 -> 9.9000006
A65: Mario Kart 64 | B65: N64 | C65: 1996 | D65: Racing | E65: Nintendo | F65: 5.55 | G65: 1.94 | H65: 2.23 | I65: 0.15 | J65: 9.87 | N65: Nintendo | P65: =IF(AND(OR(Dashboard!$B$5="All",D65=Dashboard!$B$5),OR(Dashboard!$D$5="All",N65=Dashboard!$D$5),OR(AND(C65<>"",C65>=Dashboard!$F$5,C65<=Dashboard!$H$5),AND(C65="",Dashboard!$F$5<=1980,Dashboard!$H$5>=2016))),1,0) -> 1 | Q65: =J65*P65+ROW()*0.00000001 -> 9.8700006
A66: Halo: Reach | B66: X360 | C66: 2010 | D66: Shooter | E66: Microsoft Game Studios | F66: 7.04 | G66: 1.95 | H66: 0.08 | I66: 0.79 | J66: 9.86 | K66: 91 | L66: 7.9 | M66: M | N66: Microsoft | O66: 90+ | P66: =IF(AND(OR(Dashboard!$B$5="All",D66=Dashboard!$B$5),OR(Dashboard!$D$5="All",N66=Dashboard!$D$5),OR(AND(C66<>"",C66>=Dashboard!$F$5,C66<=Dashboard!$H$5),AND(C66="",Dashboard!$F$5<=1980,Dashboard!$H$5>=2016))),1,0) -> 1 | Q66: =J66*P66+ROW()*0.00000001 -> 9.8600007
A67: Final Fantasy VII | B67: PS | C67: 1997 | D67: Role-Playing | E67: Sony Computer Entertainment | F67: 3.01 | G67: 2.47 | H67: 3.28 | I67: 0.96 | J67: 9.72 | K67: 92 | L67: 9.2 | M67: T | N67: Sony | O67: 90+ | P67: =IF(AND(OR(Dashboard!$B$5="All",D67=Dashboard!$B$5),OR(Dashboard!$D$5="All",N67=Dashboard!$D$5),OR(AND(C67<>"",C67>=Dashboard!$F$5,C67<=Dashboard!$H$5),AND(C67="",Dashboard!$F$5<=1980,Dashboard!$H$5>=2016))),1,0) -> 1 | Q67: =J67*P67+ROW()*0.00000001 -> 9.7200007
A68: Halo 4 | B68: X360 | C68: 2012 | D68: Shooter | E68: Microsoft Game Studios | F68: 6.65 | G68: 2.28 | H68: 0.04 | I68: 0.74 | J68: 9.71 | K68: 87 | L68: 7 | M68: M | N68: Microsoft | O68: 80-89 | P68: =IF(AND(OR(Dashboard!$B$5="All",D68=Dashboard!$B$5),OR(Dashboard!$D$5="All",N68=Dashboard!$D$5),OR(AND(C68<>"",C68>=Dashboard!$F$5,C68<=Dashboard!$H$5),AND(C68="",Dashboard!$F$5<=1980,Dashboard!$H$5>=2016))),1,0) -> 1 | Q68: =J68*P68+ROW()*0.00000001 -> 9.7100007
A69: Gran Turismo 2 | B69: PS | C69: 1999 | D69: Racing | E69: Sony Computer Entertainment | F69: 3.88 | G69: 3.42 | H69: 1.69 | I69: 0.5 | J69: 9.49 | K69: 93 | L69: 9 | M69: T | N69: Sony | O69: 90+ | P69: =IF(AND(OR(Dashboard!$B$5="All",D69=Dashboard!$B$5),OR(Dashboard!$D$5="All",N69=Dashboard!$D$5),OR(AND(C69<>"",C69>=Dashboard!$F$5,C69<=Dashboard!$H$5),AND(C69="",Dashboard!$F$5<=1980,Dashboard!$H$5>=2016))),1,0) -> 1 | Q69: =J69*P69+ROW()*0.00000001 -> 9.4900007
A70: Just Dance 2 | B70: Wii | C70: 2010 | D70: Misc | E70: Ubisoft | F70: 5.8 | G70: 2.85 | H70: 0.01 | I70: 0.78 | J70: 9.44 | K70: 74 | L70: 7.3 | M70: E10+ | N70: Nintendo | O70: 70-79 | P70: =IF(AND(OR(Dashboard!$B$5="All",D70=Dashboard!$B$5),OR(Dashboard!$D$5="All",N70=Dashboard!$D$5),OR(AND(C70<>"",C70>=Dashboard!$F$5,C70<=Dashboard!$H$5),AND(C70="",Dashboard!$F$5<=1980,Dashboard!$H$5>=2016))),1,0) -> 1 | Q70: =J70*P70+ROW()*0.00000001 -> 9.4400007
A71: Call of Duty: Ghosts | B71: PS3 | C71: 2013 | D71: Shooter | E71: Activision | F71: 4.1 | G71: 3.63 | H71: 0.38 | I71: 1.25 | J71: 9.36 | K71: 71 | L71: 2.6 | M71: M | N71: Sony | O71: 70-79 | P71: =IF(AND(OR(Dashboard!$B$5="All",D71=Dashboard!$B$5),OR(Dashboard!$D$5="All",N71=Dashboard!$D$5),OR(AND(C71<>"",C71>=Dashboard!$F$5,C71<=Dashboard!$H$5),AND(C71="",Dashboard!$F$5<=1980,Dashboard!$H$5>=2016))),1,0) -> 1 | Q71: =J71*P71+ROW()*0.00000001 -> 9.3600007
A72: Call of Duty 4: Modern Warfare | B72: X360 | C72: 2007 | D72: Shooter | E72: Activision | F72: 5.93 | G72: 2.36 | H72: 0.13 | I72: 0.9 | J72: 9.31 | K72: 94 | L72: 8.4 | M72: M | N72: Microsoft | O72: 90+ | P72: =IF(AND(OR(Dashboard!$B$5="All",D72=Dashboard!$B$5),OR(Dashboard!$D$5="All",N72=Dashboard!$D$5),OR(AND(C72<>"",C72>=Dashboard!$F$5,C72<=Dashboard!$H$5),AND(C72="",Dashboard!$F$5<=1980,Dashboard!$H$5>=2016))),1,0) -> 1 | Q72: =J72*P72+ROW()*0.00000001 -> 9.3100007
A73: Donkey Kong Country | B73: SNES | C73: 1994 | D73: Platform | E73: Nintendo | F73: 4.36 | G73: 1.71 | H73: 3 | I73: 0.23 | J73: 9.3 | N73: Nintendo | P73: =IF(AND(OR(Dashboard!$B$5="All",D73=Dashboard!$B$5),OR(Dashboard!$D$5="All",N73=Dashboard!$D$5),OR(AND(C73<>"",C73>=Dashboard!$F$5,C73<=Dashboard!$H$5),AND(C73="",Dashboard!$F$5<=1980,Dashboard!$H$5>=2016))),1,0) -> 1 | Q73: =J73*P73+ROW()*0.00000001 -> 9.3000007
A74: Minecraft | B74: X360 | C74: 2013 | D74: Misc | E74: Microsoft Game Studios | F74: 5.7 | G74: 2.65 | H74: 0.02 | I74: 0.81 | J74: 9.18 | N74: Microsoft | P74: =IF(AND(OR(Dashboard!$B$5="All",D74=Dashboard!$B$5),OR(Dashboard!$D$5="All",N74=Dashboard!$D$5),OR(AND(C74<>"",C74>=Dashboard!$F$5,C74<=Dashboard!$H$5),AND(C74="",Dashboard!$F$5<=1980,Dashboard!$H$5>=2016))),1,0) -> 1 | Q74: =J74*P74+ROW()*0.00000001 -> 9.1800007
A75: Animal Crossing: New Leaf | B75: 3DS | C75: 2012 | D75: Simulation | E75: Nintendo | F75: 2.03 | G75: 2.36 | H75: 4.39 | I75: 0.39 | J75: 9.16 | K75: 88 | L75: 8.7 | M75: E | N75: Nintendo | O75: 80-89 | P75: =IF(AND(OR(Dashboard!$B$5="All",D75=Dashboard!$B$5),OR(Dashboard!$D$5="All",N75=Dashboard!$D$5),OR(AND(C75<>"",C75>=Dashboard!$F$5,C75<=Dashboard!$H$5),AND(C75="",Dashboard!$F$5<=1980,Dashboard!$H$5>=2016))),1,0) -> 1 | Q75: =J75*P75+ROW()*0.00000001 -> 9.1600008
A76: Mario Party DS | B76: DS | C76: 2007 | D76: Misc | E76: Nintendo | F76: 4.4 | G76: 1.85 | H76: 1.98 | I76: 0.68 | J76: 8.91 | K76: 72 | L76: 7.8 | M76: E | N76: Nintendo | O76: 70-79 | P76: =IF(AND(OR(Dashboard!$B$5="All",D76=Dashboard!$B$5),OR(Dashboard!$D$5="All",N76=Dashboard!$D$5),OR(AND(C76<>"",C76>=Dashboard!$F$5,C76<=Dashboard!$H$5),AND(C76="",Dashboard!$F$5<=1980,Dashboard!$H$5>=2016))),1,0) -> 1 | Q76: =J76*P76+ROW()*0.00000001 -> 8.9100008
A77: The Elder Scrolls V: Skyrim | B77: X360 | C77: 2011 | D77: Role-Playing | E77: Bethesda Softworks | F77: 5.05 | G77: 2.79 | H77: 0.1 | I77: 0.85 | J77: 8.79 | K77: 96 | L77: 8.4 | M77: M | N77: Microsoft | O77: 90+ | P77: =IF(AND(OR(Dashboard!$B$5="All",D77=Dashboard!$B$5),OR(Dashboard!$D$5="All",N77=Dashboard!$D$5),OR(AND(C77<>"",C77>=Dashboard!$F$5,C77<=Dashboard!$H$5),AND(C77="",Dashboard!$F$5<=1980,Dashboard!$H$5>=2016))),1,0) -> 1 | Q77: =J77*P77+ROW()*0.00000001 -> 8.7900008
A78: Super Mario Kart | B78: SNES | C78: 1992 | D78: Racing | E78: Nintendo | F78: 3.54 | G78: 1.24 | H78: 3.81 | I78: 0.18 | J78: 8.76 | N78: Nintendo | P78: =IF(AND(OR(Dashboard!$B$5="All",D78=Dashboard!$B$5),OR(Dashboard!$D$5="All",N78=Dashboard!$D$5),OR(AND(C78<>"",C78>=Dashboard!$F$5,C78<=Dashboard!$H$5),AND(C78="",Dashboard!$F$5<=1980,Dashboard!$H$5>=2016))),1,0) -> 1 | Q78: =J78*P78+ROW()*0.00000001 -> 8.7600008
A79: FIFA 16 | B79: PS4 | C79: 2015 | D79: Sports | E79: Electronic Arts | F79: 1.12 | G79: 6.12 | H79: 0.06 | I79: 1.28 | J79: 8.57 | K79: 82 | L79: 4.3 | M79: E | N79: Sony | O79: 80-89 | P79: =IF(AND(OR(Dashboard!$B$5="All",D79=Dashboard!$B$5),OR(Dashboard!$D$5="All",N79=Dashboard!$D$5),OR(AND(C79<>"",C79>=Dashboard!$F$5,C79<=Dashboard!$H$5),AND(C79="",Dashboard!$F$5<=1980,Dashboard!$H$5>=2016))),1,0) -> 1 | Q79: =J79*P79+ROW()*0.00000001 -> 8.5700008
A80: Halo 2 | B80: XB | C80: 2004 | D80: Shooter | E80: Microsoft Game Studios | F80: 6.82 | G80: 1.53 | H80: 0.05 | I80: 0.08 | J80: 8.49 | K80: 95 | L80: 8.2 | M80: M | N80: Microsoft | O80: 90+ | P80: =IF(AND(OR(Dashboard!$B$5="All",D80=Dashboard!$B$5),OR(Dashboard!$D$5="All",N80=Dashboard!$D$5),OR(AND(C80<>"",C80>=Dashboard!$F$5,C80<=Dashboard!$H$5),AND(C80="",Dashboard!$F$5<=1980,Dashboard!$H$5>=2016))),1,0) -> 1 | Q80: =J80*P80+ROW()*0.00000001 -> 8.4900008
A81: Wii Party | B81: Wii | C81: 2010 | D81: Misc | E81: Nintendo | F81: 1.75 | G81: 3.47 | H81: 2.49 | I81: 0.67 | J81: 8.38 | K81: 68 | L81: 7.4 | M81: E | N81: Nintendo | O81: 60-69 | P81: =IF(AND(OR(Dashboard!$B$5="All",D81=Dashboard!$B$5),OR(Dashboard!$D$5="All",N81=Dashboard!$D$5),OR(AND(C81<>"",C81>=Dashboard!$F$5,C81<=Dashboard!$H$5),AND(C81="",Dashboard!$F$5<=1980,Dashboard!$H$5>=2016))),1,0) -> 1 | Q81: =J81*P81+ROW()*0.00000001 -> 8.3800008
A82: Mario Party 8 | B82: Wii | C82: 2007 | D82: Misc | E82: Nintendo | F82: 3.74 | G82: 2.24 | H82: 1.58 | I82: 0.7 | J82: 8.27 | K82: 62 | L82: 6.3 | M82: E | N82: Nintendo | O82: 60-69 | P82: =IF(AND(OR(Dashboard!$B$5="All",D82=Dashboard!$B$5),OR(Dashboard!$D$5="All",N82=Dashboard!$D$5),OR(AND(C82<>"",C82>=Dashboard!$F$5,C82<=Dashboard!$H$5),AND(C82="",Dashboard!$F$5<=1980,Dashboard!$H$5>=2016))),1,0) -> 1 | Q82: =J82*P82+ROW()*0.00000001 -> 8.2700008
A83: FIFA Soccer 13 | B83: PS3 | C83: 2012 | D83: Action | E83: Electronic Arts | F83: 1.06 | G83: 5.01 | H83: 0.13 | I83: 1.97 | J83: 8.16 | K83: 88 | L83: 6.6 | M83: E | N83: Sony | O83: 80-89 | P83: =IF(AND(OR(Dashboard!$B$5="All",D83=Dashboard!$B$5),OR(Dashboard!$D$5="All",N83=Dashboard!$D$5),OR(AND(C83<>"",C83>=Dashboard!$F$5,C83<=Dashboard!$H$5),AND(C83="",Dashboard!$F$5<=1980,Dashboard!$H$5>=2016))),1,0) -> 1 | Q83: =J83*P83+ROW()*0.00000001 -> 8.1600008
A84: GoldenEye 007 | B84: N64 | C84: 1997 | D84: Shooter | E84: Nintendo | F84: 5.8 | G84: 2.01 | H84: 0.13 | I84: 0.15 | J84: 8.09 | N84: Nintendo | P84: =IF(AND(OR(Dashboard!$B$5="All",D84=Dashboard!$B$5),OR(Dashboard!$D$5="All",N84=Dashboard!$D$5),OR(AND(C84<>"",C84>=Dashboard!$F$5,C84<=Dashboard!$H$5),AND(C84="",Dashboard!$F$5<=1980,Dashboard!$H$5>=2016))),1,0) -> 1 | Q84: =J84*P84+ROW()*0.00000001 -> 8.0900008
A85: Pokemon Black 2/Pokemon White 2 | B85: DS | C85: 2012 | D85: Role-Playing | E85: Nintendo | F85: 2.79 | G85: 1.72 | H85: 3.14 | I85: 0.41 | J85: 8.07 | N85: Nintendo | P85: =IF(AND(OR(Dashboard!$B$5="All",D85=Dashboard!$B$5),OR(Dashboard!$D$5="All",N85=Dashboard!$D$5),OR(AND(C85<>"",C85>=Dashboard!$F$5,C85<=Dashboard!$H$5),AND(C85="",Dashboard!$F$5<=1980,Dashboard!$H$5>=2016))),1,0) -> 1 | Q85: =J85*P85+ROW()*0.00000001 -> 8.0700008
A86: Final Fantasy X | B86: PS2 | C86: 2001 | D86: Role-Playing | E86: Sony Computer Entertainment | F86: 2.91 | G86: 2.07 | H86: 2.73 | I86: 0.33 | J86: 8.05 | K86: 92 | L86: 8.7 | M86: T | N86: Sony | O86: 90+ | P86: =IF(AND(OR(Dashboard!$B$5="All",D86=Dashboard!$B$5),OR(Dashboard!$D$5="All",N86=Dashboard!$D$5),OR(AND(C86<>"",C86>=Dashboard!$F$5,C86<=Dashboard!$H$5),AND(C86="",Dashboard!$F$5<=1980,Dashboard!$H$5>=2016))),1,0) -> 1 | Q86: =J86*P86+ROW()*0.00000001 -> 8.0500009
A87: The Sims 3 | B87: PC | C87: 2009 | D87: Simulation | E87: Electronic Arts | F87: 0.99 | G87: 6.42 | H87: 0 | I87: 0.6 | J87: 8.01 | K87: 86 | L87: 7.6 | M87: T | N87: PC | O87: 80-89 | P87: =IF(AND(OR(Dashboard!$B$5="All",D87=Dashboard!$B$5),OR(Dashboard!$D$5="All",N87=Dashboard!$D$5),OR(AND(C87<>"",C87>=Dashboard!$F$5,C87<=Dashboard!$H$5),AND(C87="",Dashboard!$F$5<=1980,Dashboard!$H$5>=2016))),1,0) -> 1 | Q87: =J87*P87+ROW()*0.00000001 -> 8.0100009
A88: Mario & Sonic at the Olympic Games | B88: Wii | C88: 2007 | D88: Sports | E88: Sega | F88: 2.57 | G88: 3.86 | H88: 0.66 | I88: 0.91 | J88: 7.99 | N88: Nintendo | P88: =IF(AND(OR(Dashboard!$B$5="All",D88=Dashboard!$B$5),OR(Dashboard!$D$5="All",N88=Dashboard!$D$5),OR(AND(C88<>"",C88>=Dashboard!$F$5,C88<=Dashboard!$H$5),AND(C88="",Dashboard!$F$5<=1980,Dashboard!$H$5>=2016))),1,0) -> 1 | Q88: =J88*P88+ROW()*0.00000001 -> 7.9900009
A89: Star Wars Battlefront (2015) | B89: PS4 | C89: 2015 | D89: Shooter | E89: Electronic Arts | F89: 2.99 | G89: 3.49 | H89: 0.22 | I89: 1.28 | J89: 7.98 | N89: Sony | P89: =IF(AND(OR(Dashboard!$B$5="All",D89=Dashboard!$B$5),OR(Dashboard!$D$5="All",N89=Dashboard!$D$5),OR(AND(C89<>"",C89>=Dashboard!$F$5,C89<=Dashboard!$H$5),AND(C89="",Dashboard!$F$5<=1980,Dashboard!$H$5>=2016))),1,0) -> 1 | Q89: =J89*P89+ROW()*0.00000001 -> 7.9800009
A90: Final Fantasy VIII | B90: PS | C90: 1999 | D90: Role-Playing | E90: Square Enix | F90: 2.28 | G90: 1.72 | H90: 3.63 | I90: 0.23 | J90: 7.86 | K90: 90 | L90: 8.6 | M90: T | N90: Sony | O90: 80-89 | P90: =IF(AND(OR(Dashboard!$B$5="All",D90=Dashboard!$B$5),OR(Dashboard!$D$5="All",N90=Dashboard!$D$5),OR(AND(C90<>"",C90>=Dashboard!$F$5,C90<=Dashboard!$H$5),AND(C90="",Dashboard!$F$5<=1980,Dashboard!$H$5>=2016))),1,0) -> 1 | Q90: =J90*P90+ROW()*0.00000001 -> 7.8600009
A91: Pac-Man | B91: 2600 | C91: 1982 | D91: Puzzle | E91: Atari | F91: 7.28 | G91: 0.45 | H91: 0 | I91: 0.08 | J91: 7.81 | N91: Other | P91: =IF(AND(OR(Dashboard!$B$5="All",D91=Dashboard!$B$5),OR(Dashboard!$D$5="All",N91=Dashboard!$D$5),OR(AND(C91<>"",C91>=Dashboard!$F$5,C91<=Dashboard!$H$5),AND(C91="",Dashboard!$F$5<=1980,Dashboard!$H$5>=2016))),1,0) -> 1 | Q91: =J91*P91+ROW()*0.00000001 -> 7.8100009
A92: Pokémon Platinum Version | B92: DS | C92: 2008 | D92: Role-Playing | E92: Nintendo | F92: 2.76 | G92: 1.72 | H92: 2.69 | I92: 0.54 | J92: 7.72 | K92: 83 | L92: 8.5 | M92: E | N92: Nintendo | O92: 80-89 | P92: =IF(AND(OR(Dashboard!$B$5="All",D92=Dashboard!$B$5),OR(Dashboard!$D$5="All",N92=Dashboard!$D$5),OR(AND(C92<>"",C92>=Dashboard!$F$5,C92<=Dashboard!$H$5),AND(C92="",Dashboard!$F$5<=1980,Dashboard!$H$5>=2016))),1,0) -> 1 | Q92: =J92*P92+ROW()*0.00000001 -> 7.7200009
A93: Grand Theft Auto: Liberty City Stories | B93: PSP | C93: 2005 | D93: Action | E93: Take-Two Interactive | F93: 2.9 | G93: 2.81 | H93: 0.24 | I93: 1.73 | J93: 7.69 | K93: 88 | L93: 7.6 | M93: M | N93: Sony | O93: 80-89 | P93: =IF(AND(OR(Dashboard!$B$5="All",D93=Dashboard!$B$5),OR(Dashboard!$D$5="All",N93=Dashboard!$D$5),OR(AND(C93<>"",C93>=Dashboard!$F$5,C93<=Dashboard!$H$5),AND(C93="",Dashboard!$F$5<=1980,Dashboard!$H$5>=2016))),1,0) -> 1 | Q93: =J93*P93+ROW()*0.00000001 -> 7.6900009
A94: Call of Duty: Advanced Warfare | B94: PS4 | C94: 2014 | D94: Shooter | E94: Activision | F94: 2.81 | G94: 3.48 | H94: 0.14 | I94: 1.23 | J94: 7.66 | K94: 83 | L94: 5.7 | M94: M | N94: Sony | O94: 80-89 | P94: =IF(AND(OR(Dashboard!$B$5="All",D94=Dashboard!$B$5),OR(Dashboard!$D$5="All",N94=Dashboard!$D$5),OR(AND(C94<>"",C94>=Dashboard!$F$5,C94<=Dashboard!$H$5),AND(C94="",Dashboard!$F$5<=1980,Dashboard!$H$5>=2016))),1,0) -> 1 | Q94: =J94*P94+ROW()*0.00000001 -> 7.6600009
A95: The Legend of Zelda: Ocarina of Time | B95: N64 | C95: 1998 | D95: Action | E95: Nintendo | F95: 4.1 | G95: 1.89 | H95: 1.45 | I95: 0.16 | J95: 7.6 | N95: Nintendo | P95: =IF(AND(OR(Dashboard!$B$5="All",D95=Dashboard!$B$5),OR(Dashboard!$D$5="All",N95=Dashboard!$D$5),OR(AND(C95<>"",C95>=Dashboard!$F$5,C95<=Dashboard!$H$5),AND(C95="",Dashboard!$F$5<=1980,Dashboard!$H$5>=2016))),1,0) -> 1 | Q95: =J95*P95+ROW()*0.00000001 -> 7.600001
A96: FIFA 17 | B96: PS4 | C96: 2016 | D96: Sports | E96: Electronic Arts | F96: 0.66 | G96: 5.75 | H96: 0.08 | I96: 1.11 | J96: 7.59 | K96: 85 | L96: 5 | M96: E | N96: Sony | O96: 80-89 | P96: =IF(AND(OR(Dashboard!$B$5="All",D96=Dashboard!$B$5),OR(Dashboard!$D$5="All",N96=Dashboard!$D$5),OR(AND(C96<>"",C96>=Dashboard!$F$5,C96<=Dashboard!$H$5),AND(C96="",Dashboard!$F$5<=1980,Dashboard!$H$5>=2016))),1,0) -> 1 | Q96: =J96*P96+ROW()*0.00000001 -> 7.590001
A97: Crash Bandicoot 2: Cortex Strikes Back | B97: PS | C97: 1997 | D97: Platform | E97: Sony Computer Entertainment | F97: 3.78 | G97: 2.17 | H97: 1.31 | I97: 0.31 | J97: 7.58 | N97: Sony | P97: =IF(AND(OR(Dashboard!$B$5="All",D97=Dashboard!$B$5),OR(Dashboard!$D$5="All",N97=Dashboard!$D$5),OR(AND(C97<>"",C97>=Dashboard!$F$5,C97<=Dashboard!$H$5),AND(C97="",Dashboard!$F$5<=1980,Dashboard!$H$5>=2016))),1,0) -> 1 | Q97: =J97*P97+ROW()*0.00000001 -> 7.580001
A98: Super Smash Bros. for Wii U and 3DS | B98: 3DS | C98: 2014 | D98: Fighting | E98: Nintendo | F98: 3.27 | G98: 1.37 | H98: 2.43 | I98: 0.48 | J98: 7.55 | N98: Nintendo | P98: =IF(AND(OR(Dashboard!$B$5="All",D98=Dashboard!$B$5),OR(Dashboard!$D$5="All",N98=Dashboard!$D$5),OR(AND(C98<>"",C98>=Dashboard!$F$5,C98<=Dashboard!$H$5),AND(C98="",Dashboard!$F$5<=1980,Dashboard!$H$5>=2016))),1,0) -> 1 | Q98: =J98*P98+ROW()*0.00000001 -> 7.550001
A99: Super Mario Galaxy 2 | B99: Wii | C99: 2010 | D99: Platform | E99: Nintendo | F99: 3.56 | G99: 2.35 | H99: 0.98 | I99: 0.62 | J99: 7.51 | K99: 97 | L99: 9.1 | M99: E | N99: Nintendo | O99: 90+ | P99: =IF(AND(OR(Dashboard!$B$5="All",D99=Dashboard!$B$5),OR(Dashboard!$D$5="All",N99=Dashboard!$D$5),OR(AND(C99<>"",C99>=Dashboard!$F$5,C99<=Dashboard!$H$5),AND(C99="",Dashboard!$F$5<=1980,Dashboard!$H$5>=2016))),1,0) -> 1 | Q99: =J99*P99+ROW()*0.00000001 -> 7.510001
A100: Super Mario Bros. 2 | B100: NES | C100: 1988 | D100: Platform | E100: Nintendo | F100: 5.39 | G100: 1.18 | H100: 0.7 | I100: 0.19 | J100: 7.46 | N100: Nintendo | P100: =IF(AND(OR(Dashboard!$B$5="All",D100=Dashboard!$B$5),OR(Dashboard!$D$5="All",N100=Dashboard!$D$5),OR(AND(C100<>"",C100>=Dashboard!$F$5,C100<=Dashboard!$H$5),AND(C100="",Dashboard!$F$5<=1980,Dashboard!$H$5>=2016))),1,0) -> 1 | Q100: =J100*P100+ROW()*0.00000001 -> 7.460001
...

Sheet Calc
A1: Helper tables feeding the Dashboard (all formulas react to the Dashboard filters). Do not edit.
A2: Genre | B2: Releases | C2: Sales (M) | D2: Avg per release (M) | F2: Year | G2: Releases | H2: Sales (M) | J2: Region | K2: Sales (M) | M2: Critic band | N2: Avg sales per release (M) | P2: Platform | Q2: Sales (M) | R2: Sort key | T2: Rank | U2: Top platforms | V2: Sales (M) | X2: Publisher | Y2: Sales (M) | Z2: Sort key | AB2: Rank | AC2: Top publishers | AD2: Sales (M) | AF2: Rank | AG2: Top releases | AH2: Sales (M)
A3: Action | B3: =COUNTIFS(Data!$D$2:$D$16716,A3,Data!$P$2:$P$16716,1) -> 3370 | C3: =SUMIFS(Data!$J$2:$J$16716,Data!$D$2:$D$16716,A3,Data!$P$2:$P$16716,1) -> 1745.27 | D3: =IF(B3=0,0,C3/B3) -> 0.51788427 | F3: 1980 | G3: =COUNTIFS(Data!$C$2:$C$16716,F3,Data!$P$2:$P$16716,1) -> 9 | H3: =SUMIFS(Data!$J$2:$J$16716,Data!$C$2:$C$16716,F3,Data!$P$2:$P$16716,1) -> 11.38 | J3: North America | K3: =SUMIFS(Data!$F$2:$F$16716,Data!$P$2:$P$16716,1) -> 4400.84 | M3: 0-49 | N3: =IFERROR(AVERAGEIFS(Data!$J$2:$J$16716,Data!$O$2:$O$16716,M3,Data!$P$2:$P$16716,1),0) -> 0.23077273 | P3: PS2 | Q3: =SUMIFS(Data!$J$2:$J$16716,Data!$B$2:$B$16716,P3,Data!$P$2:$P$16716,1) -> 1255.64 | R3: =Q3+ROW()*0.000000001 -> 1255.64 | T3: 1 | U3: =IF(V3=0,"",INDEX($P$3:$P$33,MATCH(LARGE($R$3:$R$33,T3),$R$3:$R$33,0))) -> PS2 | V3: =INDEX($Q$3:$Q$33,MATCH(LARGE($R$3:$R$33,T3),$R$3:$R$33,0)) -> 1255.64 | X3: Nintendo | Y3: =SUMIFS(Data!$J$2:$J$16716,Data!$E$2:$E$16716,X3,Data!$P$2:$P$16716,1) -> 1788.81 | Z3: =Y3+ROW()*0.000000001 -> 1788.81 | AB3: 1 | AC3: =IF(AD3=0,"",INDEX($X$3:$X$574,MATCH(LARGE($Z$3:$Z$574,AB3),$Z$3:$Z$574,0))) -> Nintendo | AD3: =INDEX($Y$3:$Y$574,MATCH(LARGE($Z$3:$Z$574,AB3),$Z$3:$Z$574,0)) -> 1788.81 | AF3: 1 | AG3: =IF(AH3=0,"",INDEX(Data!$A$2:$A$16716,MATCH(LARGE(Data!$Q$2:$Q$16716,AF3),Data!$Q$2:$Q$16716,0))&" ("&INDEX(Data!$B$2:$B$16716,MATCH(LARGE(Data!$Q$2:$Q$16716,AF3),Data!$Q$2:$Q$16716,0))&")") -> Wii Sports (Wii) | AH3: =INDEX(Data!$J$2:$J$16716,MATCH(LARGE(Data!$Q$2:$Q$16716,AF3),Data!$Q$2:$Q$16716,0))*INDEX(Data!$P$2:$P$16716,MATCH(LARGE(Data!$Q$2:$Q$16716,AF3),Data!$Q$2:$Q$16716,0)) -> 82.53
A4: Sports | B4: =COUNTIFS(Data!$D$2:$D$16716,A4,Data!$P$2:$P$16716,1) -> 2347 | C4: =SUMIFS(Data!$J$2:$J$16716,Data!$D$2:$D$16716,A4,Data!$P$2:$P$16716,1) -> 1332 | D4: =IF(B4=0,0,C4/B4) -> 0.56753302 | F4: 1981 | G4: =COUNTIFS(Data!$C$2:$C$16716,F4,Data!$P$2:$P$16716,1) -> 46 | H4: =SUMIFS(Data!$J$2:$J$16716,Data!$C$2:$C$16716,F4,Data!$P$2:$P$16716,1) -> 35.77 | J4: Europe | K4: =SUMIFS(Data!$G$2:$G$16716,Data!$P$2:$P$16716,1) -> 2424.14 | M4: 50-59 | N4: =IFERROR(AVERAGEIFS(Data!$J$2:$J$16716,Data!$O$2:$O$16716,M4,Data!$P$2:$P$16716,1),0) -> 0.30128788 | P4: X360 | Q4: =SUMIFS(Data!$J$2:$J$16716,Data!$B$2:$B$16716,P4,Data!$P$2:$P$16716,1) -> 971.63 | R4: =Q4+ROW()*0.000000001 -> 971.63 | T4: 2 | U4: =IF(V4=0,"",INDEX($P$3:$P$33,MATCH(LARGE($R$3:$R$33,T4),$R$3:$R$33,0))) -> X360 | V4: =INDEX($Q$3:$Q$33,MATCH(LARGE($R$3:$R$33,T4),$R$3:$R$33,0)) -> 971.63 | X4: Electronic Arts | Y4: =SUMIFS(Data!$J$2:$J$16716,Data!$E$2:$E$16716,X4,Data!$P$2:$P$16716,1) -> 1116.96 | Z4: =Y4+ROW()*0.000000001 -> 1116.96 | AB4: 2 | AC4: =IF(AD4=0,"",INDEX($X$3:$X$574,MATCH(LARGE($Z$3:$Z$574,AB4),$Z$3:$Z$574,0))) -> Electronic Arts | AD4: =INDEX($Y$3:$Y$574,MATCH(LARGE($Z$3:$Z$574,AB4),$Z$3:$Z$574,0)) -> 1116.96 | AF4: 2 | AG4: =IF(AH4=0,"",INDEX(Data!$A$2:$A$16716,MATCH(LARGE(Data!$Q$2:$Q$16716,AF4),Data!$Q$2:$Q$16716,0))&" ("&INDEX(Data!$B$2:$B$16716,MATCH(LARGE(Data!$Q$2:$Q$16716,AF4),Data!$Q$2:$Q$16716,0))&")") -> Super Mario Bros. (NES) | AH4: =INDEX(Data!$J$2:$J$16716,MATCH(LARGE(Data!$Q$2:$Q$16716,AF4),Data!$Q$2:$Q$16716,0))*INDEX(Data!$P$2:$P$16716,MATCH(LARGE(Data!$Q$2:$Q$16716,AF4),Data!$Q$2:$Q$16716,0)) -> 40.24
A5: Shooter | B5: =COUNTIFS(Data!$D$2:$D$16716,A5,Data!$P$2:$P$16716,1) -> 1323 | C5: =SUMIFS(Data!$J$2:$J$16716,Data!$D$2:$D$16716,A5,Data!$P$2:$P$16716,1) -> 1052.94 | D5: =IF(B5=0,0,C5/B5) -> 0.79587302 | F5: 1982 | G5: =COUNTIFS(Data!$C$2:$C$16716,F5,Data!$P$2:$P$16716,1) -> 36 | H5: =SUMIFS(Data!$J$2:$J$16716,Data!$C$2:$C$16716,F5,Data!$P$2:$P$16716,1) -> 28.86 | J5: Japan | K5: =SUMIFS(Data!$H$2:$H$16716,Data!$P$2:$P$16716,1) -> 1297.4 | M5: 60-69 | N5: =IFERROR(AVERAGEIFS(Data!$J$2:$J$16716,Data!$O$2:$O$16716,M5,Data!$P$2:$P$16716,1),0) -> 0.37993843 | P5: PS3 | Q5: =SUMIFS(Data!$J$2:$J$16716,Data!$B$2:$B$16716,P5,Data!$P$2:$P$16716,1) -> 939.43 | R5: =Q5+ROW()*0.000000001 -> 939.43 | T5: 3 | U5: =IF(V5=0,"",INDEX($P$3:$P$33,MATCH(LARGE($R$3:$R$33,T5),$R$3:$R$33,0))) -> PS3 | V5: =INDEX($Q$3:$Q$33,MATCH(LARGE($R$3:$R$33,T5),$R$3:$R$33,0)) -> 939.43 | X5: Activision | Y5: =SUMIFS(Data!$J$2:$J$16716,Data!$E$2:$E$16716,X5,Data!$P$2:$P$16716,1) -> 738.11 | Z5: =Y5+ROW()*0.000000001 -> 738.11 | AB5: 3 | AC5: =IF(AD5=0,"",INDEX($X$3:$X$574,MATCH(LARGE($Z$3:$Z$574,AB5),$Z$3:$Z$574,0))) -> Activision | AD5: =INDEX($Y$3:$Y$574,MATCH(LARGE($Z$3:$Z$574,AB5),$Z$3:$Z$574,0)) -> 738.11 | AF5: 3 | AG5: =IF(AH5=0,"",INDEX(Data!$A$2:$A$16716,MATCH(LARGE(Data!$Q$2:$Q$16716,AF5),Data!$Q$2:$Q$16716,0))&" ("&INDEX(Data!$B$2:$B$16716,MATCH(LARGE(Data!$Q$2:$Q$16716,AF5),Data!$Q$2:$Q$16716,0))&")") -> Mario Kart Wii (Wii) | AH5: =INDEX(Data!$J$2:$J$16716,MATCH(LARGE(Data!$Q$2:$Q$16716,AF5),Data!$Q$2:$Q$16716,0))*INDEX(Data!$P$2:$P$16716,MATCH(LARGE(Data!$Q$2:$Q$16716,AF5),Data!$Q$2:$Q$16716,0)) -> 35.52
A6: Role-Playing | B6: =COUNTIFS(Data!$D$2:$D$16716,A6,Data!$P$2:$P$16716,1) -> 1500 | C6: =SUMIFS(Data!$J$2:$J$16716,Data!$D$2:$D$16716,A6,Data!$P$2:$P$16716,1) -> 934.4 | D6: =IF(B6=0,0,C6/B6) -> 0.62293333 | F6: 1983 | G6: =COUNTIFS(Data!$C$2:$C$16716,F6,Data!$P$2:$P$16716,1) -> 17 | H6: =SUMIFS(Data!$J$2:$J$16716,Data!$C$2:$C$16716,F6,Data!$P$2:$P$16716,1) -> 16.79 | J6: Other | K6: =SUMIFS(Data!$I$2:$I$16716,Data!$P$2:$P$16716,1) -> 791.26 | M6: 70-79 | N6: =IFERROR(AVERAGEIFS(Data!$J$2:$J$16716,Data!$O$2:$O$16716,M6,Data!$P$2:$P$16716,1),0) -> 0.67607509 | P6: Wii | Q6: =SUMIFS(Data!$J$2:$J$16716,Data!$B$2:$B$16716,P6,Data!$P$2:$P$16716,1) -> 908.13 | R6: =Q6+ROW()*0.000000001 -> 908.13 | T6: 4 | U6: =IF(V6=0,"",INDEX($P$3:$P$33,MATCH(LARGE($R$3:$R$33,T6),$R$3:$R$33,0))) -> Wii | V6: =INDEX($Q$3:$Q$33,MATCH(LARGE($R$3:$R$33,T6),$R$3:$R$33,0)) -> 908.13 | X6: Sony Computer Entertainment | Y6: =SUMIFS(Data!$J$2:$J$16716,Data!$E$2:$E$16716,X6,Data!$P$2:$P$16716,1) -> 631.11 | Z6: =Y6+ROW()*0.000000001 -> 631.11 | AB6: 4 | AC6: =IF(AD6=0,"",INDEX($X$3:$X$574,MATCH(LARGE($Z$3:$Z$574,AB6),$Z$3:$Z$574,0))) -> Sony Computer Entertainment | AD6: =INDEX($Y$3:$Y$574,MATCH(LARGE($Z$3:$Z$574,AB6),$Z$3:$Z$574,0)) -> 631.11 | AF6: 4 | AG6: =IF(AH6=0,"",INDEX(Data!$A$2:$A$16716,MATCH(LARGE(Data!$Q$2:$Q$16716,AF6),Data!$Q$2:$Q$16716,0))&" ("&INDEX(Data!$B$2:$B$16716,MATCH(LARGE(Data!$Q$2:$Q$16716,AF6),Data!$Q$2:$Q$16716,0))&")") -> Wii Sports Resort (Wii) | AH6: =INDEX(Data!$J$2:$J$16716,MATCH(LARGE(Data!$Q$2:$Q$16716,AF6),Data!$Q$2:$Q$16716,0))*INDEX(Data!$P$2:$P$16716,MATCH(LARGE(Data!$Q$2:$Q$16716,AF6),Data!$Q$2:$Q$16716,0)) -> 32.77
A7: Platform | B7: =COUNTIFS(Data!$D$2:$D$16716,A7,Data!$P$2:$P$16716,1) -> 887 | C7: =SUMIFS(Data!$J$2:$J$16716,Data!$D$2:$D$16716,A7,Data!$P$2:$P$16716,1) -> 828.08 | D7: =IF(B7=0,0,C7/B7) -> 0.93357384 | F7: 1984 | G7: =COUNTIFS(Data!$C$2:$C$16716,F7,Data!$P$2:$P$16716,1) -> 14 | H7: =SUMIFS(Data!$J$2:$J$16716,Data!$C$2:$C$16716,F7,Data!$P$2:$P$16716,1) -> 50.36 | M7: 80-89 | N7: =IFERROR(AVERAGEIFS(Data!$J$2:$J$16716,Data!$O$2:$O$16716,M7,Data!$P$2:$P$16716,1),0) -> 1.2463546 | P7: DS | Q7: =SUMIFS(Data!$J$2:$J$16716,Data!$B$2:$B$16716,P7,Data!$P$2:$P$16716,1) -> 807.1 | R7: =Q7+ROW()*0.000000001 -> 807.1 | T7: 5 | U7: =IF(V7=0,"",INDEX($P$3:$P$33,MATCH(LARGE($R$3:$R$33,T7),$R$3:$R$33,0))) -> DS | V7: =INDEX($Q$3:$Q$33,MATCH(LARGE($R$3:$R$33,T7),$R$3:$R$33,0)) -> 807.1 | X7: Ubisoft | Y7: =SUMIFS(Data!$J$2:$J$16716,Data!$E$2:$E$16716,X7,Data!$P$2:$P$16716,1) -> 476.07 | Z7: =Y7+ROW()*0.000000001 -> 476.07 | AB7: 5 | AC7: =IF(AD7=0,"",INDEX($X$3:$X$574,MATCH(LARGE($Z$3:$Z$574,AB7),$Z$3:$Z$574,0))) -> Ubisoft | AD7: =INDEX($Y$3:$Y$574,MATCH(LARGE($Z$3:$Z$574,AB7),$Z$3:$Z$574,0)) -> 476.07 | AF7: 5 | AG7: =IF(AH7=0,"",INDEX(Data!$A$2:$A$16716,MATCH(LARGE(Data!$Q$2:$Q$16716,AF7),Data!$Q$2:$Q$16716,0))&" ("&INDEX(Data!$B$2:$B$16716,MATCH(LARGE(Data!$Q$2:$Q$16716,AF7),Data!$Q$2:$Q$16716,0))&")") -> Pokemon Red/Pokemon Blue (GB) | AH7: =INDEX(Data!$J$2:$J$16716,MATCH(LARGE(Data!$Q$2:$Q$16716,AF7),Data!$Q$2:$Q$16716,0))*INDEX(Data!$P$2:$P$16716,MATCH(LARGE(Data!$Q$2:$Q$16716,AF7),Data!$Q$2:$Q$16716,0)) -> 31.37
A8: Misc | B8: =COUNTIFS(Data!$D$2:$D$16716,A8,Data!$P$2:$P$16716,1) -> 1750 | C8: =SUMIFS(Data!$J$2:$J$16716,Data!$D$2:$D$16716,A8,Data!$P$2:$P$16716,1) -> 803.18 | D8: =IF(B8=0,0,C8/B8) -> 0.45896 | F8: 1985 | G8: =COUNTIFS(Data!$C$2:$C$16716,F8,Data!$P$2:$P$16716,1) -> 14 | H8: =SUMIFS(Data!$J$2:$J$16716,Data!$C$2:$C$16716,F8,Data!$P$2:$P$16716,1) -> 53.94 | M8: 90+ | N8: =IFERROR(AVERAGEIFS(Data!$J$2:$J$16716,Data!$O$2:$O$16716,M8,Data!$P$2:$P$16716,1),0) -> 3.2285214 | P8: PS | Q8: =SUMIFS(Data!$J$2:$J$16716,Data!$B$2:$B$16716,P8,Data!$P$2:$P$16716,1) -> 730.68 | R8: =Q8+ROW()*0.000000001 -> 730.68 | T8: 6 | U8: =IF(V8=0,"",INDEX($P$3:$P$33,MATCH(LARGE($R$3:$R$33,T8),$R$3:$R$33,0))) -> PS | V8: =INDEX($Q$3:$Q$33,MATCH(LARGE($R$3:$R$33,T8),$R$3:$R$33,0)) -> 730.68 | X8: Take-Two Interactive | Y8: =SUMIFS(Data!$J$2:$J$16716,Data!$E$2:$E$16716,X8,Data!$P$2:$P$16716,1) -> 403.82 | Z8: =Y8+ROW()*0.000000001 -> 403.82 | AB8: 6 | AC8: =IF(AD8=0,"",INDEX($X$3:$X$574,MATCH(LARGE($Z$3:$Z$574,AB8),$Z$3:$Z$574,0))) -> Take-Two Interactive | AD8: =INDEX($Y$3:$Y$574,MATCH(LARGE($Z$3:$Z$574,AB8),$Z$3:$Z$574,0)) -> 403.82 | AF8: 6 | AG8: =IF(AH8=0,"",INDEX(Data!$A$2:$A$16716,MATCH(LARGE(Data!$Q$2:$Q$16716,AF8),Data!$Q$2:$Q$16716,0))&" ("&INDEX(Data!$B$2:$B$16716,MATCH(LARGE(Data!$Q$2:$Q$16716,AF8),Data!$Q$2:$Q$16716,0))&")") -> Tetris (GB) | AH8: =INDEX(Data!$J$2:$J$16716,MATCH(LARGE(Data!$Q$2:$Q$16716,AF8),Data!$Q$2:$Q$16716,0))*INDEX(Data!$P$2:$P$16716,MATCH(LARGE(Data!$Q$2:$Q$16716,AF8),Data!$Q$2:$Q$16716,0)) -> 30.26
A9: Racing | B9: =COUNTIFS(Data!$D$2:$D$16716,A9,Data!$P$2:$P$16716,1) -> 1249 | C9: =SUMIFS(Data!$J$2:$J$16716,Data!$D$2:$D$16716,A9,Data!$P$2:$P$16716,1) -> 728.9 | D9: =IF(B9=0,0,C9/B9) -> 0.58358687 | F9: 1986 | G9: =COUNTIFS(Data!$C$2:$C$16716,F9,Data!$P$2:$P$16716,1) -> 21 | H9: =SUMIFS(Data!$J$2:$J$16716,Data!$C$2:$C$16716,F9,Data!$P$2:$P$16716,1) -> 37.07 | P9: GBA | Q9: =SUMIFS(Data!$J$2:$J$16716,Data!$B$2:$B$16716,P9,Data!$P$2:$P$16716,1) -> 318.5 | R9: =Q9+ROW()*0.000000001 -> 318.5 | T9: 7 | U9: =IF(V9=0,"",INDEX($P$3:$P$33,MATCH(LARGE($R$3:$R$33,T9),$R$3:$R$33,0))) -> GBA | V9: =INDEX($Q$3:$Q$33,MATCH(LARGE($R$3:$R$33,T9),$R$3:$R$33,0)) -> 318.5 | X9: THQ | Y9: =SUMIFS(Data!$J$2:$J$16716,Data!$E$2:$E$16716,X9,Data!$P$2:$P$16716,1) -> 338.44 | Z9: =Y9+ROW()*0.000000001 -> 338.44 | AB9: 7 | AC9: =IF(AD9=0,"",INDEX($X$3:$X$574,MATCH(LARGE($Z$3:$Z$574,AB9),$Z$3:$Z$574,0))) -> THQ | AD9: =INDEX($Y$3:$Y$574,MATCH(LARGE($Z$3:$Z$574,AB9),$Z$3:$Z$574,0)) -> 338.44 | AF9: 7 | AG9: =IF(AH9=0,"",INDEX(Data!$A$2:$A$16716,MATCH(LARGE(Data!$Q$2:$Q$16716,AF9),Data!$Q$2:$Q$16716,0))&" ("&INDEX(Data!$B$2:$B$16716,MATCH(LARGE(Data!$Q$2:$Q$16716,AF9),Data!$Q$2:$Q$16716,0))&")") -> New Super Mario Bros. (DS) | AH9: =INDEX(Data!$J$2:$J$16716,MATCH(LARGE(Data!$Q$2:$Q$16716,AF9),Data!$Q$2:$Q$16716,0))*INDEX(Data!$P$2:$P$16716,MATCH(LARGE(Data!$Q$2:$Q$16716,AF9),Data!$Q$2:$Q$16716,0)) -> 29.8
A10: Fighting | B10: =COUNTIFS(Data!$D$2:$D$16716,A10,Data!$P$2:$P$16716,1) -> 849 | C10: =SUMIFS(Data!$J$2:$J$16716,Data!$D$2:$D$16716,A10,Data!$P$2:$P$16716,1) -> 447.48 | D10: =IF(B10=0,0,C10/B10) -> 0.52706714 | F10: 1987 | G10: =COUNTIFS(Data!$C$2:$C$16716,F10,Data!$P$2:$P$16716,1) -> 16 | H10: =SUMIFS(Data!$J$2:$J$16716,Data!$C$2:$C$16716,F10,Data!$P$2:$P$16716,1) -> 21.74 | P10: PS4 | Q10: =SUMIFS(Data!$J$2:$J$16716,Data!$B$2:$B$16716,P10,Data!$P$2:$P$16716,1) -> 314.23 | R10: =Q10+ROW()*0.000000001 -> 314.23 | T10: 8 | U10: =IF(V10=0,"",INDEX($P$3:$P$33,MATCH(LARGE($R$3:$R$33,T10),$R$3:$R$33,0))) -> PS4 | V10: =INDEX($Q$3:$Q$33,MATCH(LARGE($R$3:$R$33,T10),$R$3:$R$33,0)) -> 314.23 | X10: Konami Digital Entertainment | Y10: =SUMIFS(Data!$J$2:$J$16716,Data!$E$2:$E$16716,X10,Data!$P$2:$P$16716,1) -> 282.39 | Z10: =Y10+ROW()*0.000000001 -> 282.39 | AB10: 8 | AC10: =IF(AD10=0,"",INDEX($X$3:$X$574,MATCH(LARGE($Z$3:$Z$574,AB10),$Z$3:$Z$574,0))) -> Konami Digital Entertainment | AD10: =INDEX($Y$3:$Y$574,MATCH(LARGE($Z$3:$Z$574,AB10),$Z$3:$Z$574,0)) -> 282.39 | AF10: 8 | AG10: =IF(AH10=0,"",INDEX(Data!$A$2:$A$16716,MATCH(LARGE(Data!$Q$2:$Q$16716,AF10),Data!$Q$2:$Q$16716,0))&" ("&INDEX(Data!$B$2:$B$16716,MATCH(LARGE(Data!$Q$2:$Q$16716,AF10),Data!$Q$2:$Q$16716,0))&")") -> Wii Play (Wii) | AH10: =INDEX(Data!$J$2:$J$16716,MATCH(LARGE(Data!$Q$2:$Q$16716,AF10),Data!$Q$2:$Q$16716,0))*INDEX(Data!$P$2:$P$16716,MATCH(LARGE(Data!$Q$2:$Q$16716,AF10),Data!$Q$2:$Q$16716,0)) -> 28.92
A11: Simulation | B11: =COUNTIFS(Data!$D$2:$D$16716,A11,Data!$P$2:$P$16716,1) -> 874 | C11: =SUMIFS(Data!$J$2:$J$16716,Data!$D$2:$D$16716,A11,Data!$P$2:$P$16716,1) -> 390.42 | D11: =IF(B11=0,0,C11/B11) -> 0.44670481 | F11: 1988 | G11: =COUNTIFS(Data!$C$2:$C$16716,F11,Data!$P$2:$P$16716,1) -> 15 | H11: =SUMIFS(Data!$J$2:$J$16716,Data!$C$2:$C$16716,F11,Data!$P$2:$P$16716,1) -> 47.22 | P11: PSP | Q11: =SUMIFS(Data!$J$2:$J$16716,Data!$B$2:$B$16716,P11,Data!$P$2:$P$16716,1) -> 294.3 | R11: =Q11+ROW()*0.000000001 -> 294.3 | T11: 9 | U11: =IF(V11=0,"",INDEX($P$3:$P$33,MATCH(LARGE($R$3:$R$33,T11),$R$3:$R$33,0))) -> PSP | V11: =INDEX($Q$3:$Q$33,MATCH(LARGE($R$3:$R$33,T11),$R$3:$R$33,0)) -> 294.3 | X11: Sega | Y11: =SUMIFS(Data!$J$2:$J$16716,Data!$E$2:$E$16716,X11,Data!$P$2:$P$16716,1) -> 270.83 | Z11: =Y11+ROW()*0.000000001 -> 270.83 | AB11: 9 | AC11: =IF(AD11=0,"",INDEX($X$3:$X$574,MATCH(LARGE($Z$3:$Z$574,AB11),$Z$3:$Z$574,0))) -> Sega | AD11: =INDEX($Y$3:$Y$574,MATCH(LARGE($Z$3:$Z$574,AB11),$Z$3:$Z$574,0)) -> 270.83 | AF11: 9 | AG11: =IF(AH11=0,"",INDEX(Data!$A$2:$A$16716,MATCH(LARGE(Data!$Q$2:$Q$16716,AF11),Data!$Q$2:$Q$16716,0))&" ("&INDEX(Data!$B$2:$B$16716,MATCH(LARGE(Data!$Q$2:$Q$16716,AF11),Data!$Q$2:$Q$16716,0))&")") -> New Super Mario Bros. Wii (Wii) | AH11: =INDEX(Data!$J$2:$J$16716,MATCH(LARGE(Data!$Q$2:$Q$16716,AF11),Data!$Q$2:$Q$16716,0))*INDEX(Data!$P$2:$P$16716,MATCH(LARGE(Data!$Q$2:$Q$16716,AF11),Data!$Q$2:$Q$16716,0)) -> 28.32
A12: Puzzle | B12: =COUNTIFS(Data!$D$2:$D$16716,A12,Data!$P$2:$P$16716,1) -> 580 | C12: =SUMIFS(Data!$J$2:$J$16716,Data!$D$2:$D$16716,A12,Data!$P$2:$P$16716,1) -> 243.02 | D12: =IF(B12=0,0,C12/B12) -> 0.419 | F12: 1989 | G12: =COUNTIFS(Data!$C$2:$C$16716,F12,Data!$P$2:$P$16716,1) -> 17 | H12: =SUMIFS(Data!$J$2:$J$16716,Data!$C$2:$C$16716,F12,Data!$P$2:$P$16716,1) -> 73.45 | P12: PC | Q12: =SUMIFS(Data!$J$2:$J$16716,Data!$B$2:$B$16716,P12,Data!$P$2:$P$16716,1) -> 260.3 | R12: =Q12+ROW()*0.000000001 -> 260.3 | T12: 10 | U12: =IF(V12=0,"",INDEX($P$3:$P$33,MATCH(LARGE($R$3:$R$33,T12),$R$3:$R$33,0))) -> PC | V12: =INDEX($Q$3:$Q$33,MATCH(LARGE($R$3:$R$33,T12),$R$3:$R$33,0)) -> 260.3 | X12: Namco Bandai Games | Y12: =SUMIFS(Data!$J$2:$J$16716,Data!$E$2:$E$16716,X12,Data!$P$2:$P$16716,1) -> 254.62 | Z12: =Y12+ROW()*0.000000001 -> 254.62 | AB12: 10 | AC12: =IF(AD12=0,"",INDEX($X$3:$X$574,MATCH(LARGE($Z$3:$Z$574,AB12),$Z$3:$Z$574,0))) -> Namco Bandai Games | AD12: =INDEX($Y$3:$Y$574,MATCH(LARGE($Z$3:$Z$574,AB12),$Z$3:$Z$574,0)) -> 254.62 | AF12: 10 | AG12: =IF(AH12=0,"",INDEX(Data!$A$2:$A$16716,MATCH(LARGE(Data!$Q$2:$Q$16716,AF12),Data!$Q$2:$Q$16716,0))&" ("&INDEX(Data!$B$2:$B$16716,MATCH(LARGE(Data!$Q$2:$Q$16716,AF12),Data!$Q$2:$Q$16716,0))&")") -> Duck Hunt (NES) | AH12: =INDEX(Data!$J$2:$J$16716,MATCH(LARGE(Data!$Q$2:$Q$16716,AF12),Data!$Q$2:$Q$16716,0))*INDEX(Data!$P$2:$P$16716,MATCH(LARGE(Data!$Q$2:$Q$16716,AF12),Data!$Q$2:$Q$16716,0)) -> 28.31
A13: Adventure | B13: =COUNTIFS(Data!$D$2:$D$16716,A13,Data!$P$2:$P$16716,1) -> 1303 | C13: =SUMIFS(Data!$J$2:$J$16716,Data!$D$2:$D$16716,A13,Data!$P$2:$P$16716,1) -> 237.69 | D13: =IF(B13=0,0,C13/B13) -> 0.1824175 | F13: 1990 | G13: =COUNTIFS(Data!$C$2:$C$16716,F13,Data!$P$2:$P$16716,1) -> 16 | H13: =SUMIFS(Data!$J$2:$J$16716,Data!$C$2:$C$16716,F13,Data!$P$2:$P$16716,1) -> 49.39 | P13: 3DS | Q13: =SUMIFS(Data!$J$2:$J$16716,Data!$B$2:$B$16716,P13,Data!$P$2:$P$16716,1) -> 259.09 | R13: =Q13+ROW()*0.000000001 -> 259.09 | X13: Microsoft Game Studios | Y13: =SUMIFS(Data!$J$2:$J$16716,Data!$E$2:$E$16716,X13,Data!$P$2:$P$16716,1) -> 248.32 | Z13: =Y13+ROW()*0.000000001 -> 248.32
A14: Strategy | B14: =COUNTIFS(Data!$D$2:$D$16716,A14,Data!$P$2:$P$16716,1) -> 683 | C14: =SUMIFS(Data!$J$2:$J$16716,Data!$D$2:$D$16716,A14,Data!$P$2:$P$16716,1) -> 174.5 | D14: =IF(B14=0,0,C14/B14) -> 0.25549048 | F14: 1991 | G14: =COUNTIFS(Data!$C$2:$C$16716,F14,Data!$P$2:$P$16716,1) -> 41 | H14: =SUMIFS(Data!$J$2:$J$16716,Data!$C$2:$C$16716,F14,Data!$P$2:$P$16716,1) -> 32.23 | P14: XB | Q14: =SUMIFS(Data!$J$2:$J$16716,Data!$B$2:$B$16716,P14,Data!$P$2:$P$16716,1) -> 258.26 | R14: =Q14+ROW()*0.000000001 -> 258.26 | X14: Square Enix | Y14: =SUMIFS(Data!$J$2:$J$16716,Data!$E$2:$E$16716,X14,Data!$P$2:$P$16716,1) -> 207.43 | Z14: =Y14+ROW()*0.000000001 -> 207.43
F15: 1992 | G15: =COUNTIFS(Data!$C$2:$C$16716,F15,Data!$P$2:$P$16716,1) -> 43 | H15: =SUMIFS(Data!$J$2:$J$16716,Data!$C$2:$C$16716,F15,Data!$P$2:$P$16716,1) -> 76.17 | P15: GB | Q15: =SUMIFS(Data!$J$2:$J$16716,Data!$B$2:$B$16716,P15,Data!$P$2:$P$16716,1) -> 255.45 | R15: =Q15+ROW()*0.000000001 -> 255.45 | X15: Capcom | Y15: =SUMIFS(Data!$J$2:$J$16716,Data!$E$2:$E$16716,X15,Data!$P$2:$P$16716,1) -> 200.02 | Z15: =Y15+ROW()*0.000000001 -> 200.02
F16: 1993 | G16: =COUNTIFS(Data!$C$2:$C$16716,F16,Data!$P$2:$P$16716,1) -> 60 | H16: =SUMIFS(Data!$J$2:$J$16716,Data!$C$2:$C$16716,F16,Data!$P$2:$P$16716,1) -> 45.98 | P16: NES | Q16: =SUMIFS(Data!$J$2:$J$16716,Data!$B$2:$B$16716,P16,Data!$P$2:$P$16716,1) -> 251.07 | R16: =Q16+ROW()*0.000000001 -> 251.07 | X16: Atari | Y16: =SUMIFS(Data!$J$2:$J$16716,Data!$E$2:$E$16716,X16,Data!$P$2:$P$16716,1) -> 156.83 | Z16: =Y16+ROW()*0.000000001 -> 156.83
F17: 1994 | G17: =COUNTIFS(Data!$C$2:$C$16716,F17,Data!$P$2:$P$16716,1) -> 121 | H17: =SUMIFS(Data!$J$2:$J$16716,Data!$C$2:$C$16716,F17,Data!$P$2:$P$16716,1) -> 79.18 | P17: N64 | Q17: =SUMIFS(Data!$J$2:$J$16716,Data!$B$2:$B$16716,P17,Data!$P$2:$P$16716,1) -> 218.88 | R17: =Q17+ROW()*0.000000001 -> 218.88 | X17: Warner Bros. Interactive Entertainment | Y17: =SUMIFS(Data!$J$2:$J$16716,Data!$E$2:$E$16716,X17,Data!$P$2:$P$16716,1) -> 151.79 | Z17: =Y17+ROW()*0.000000001 -> 151.79
F18: 1995 | G18: =COUNTIFS(Data!$C$2:$C$16716,F18,Data!$P$2:$P$16716,1) -> 219 | H18: =SUMIFS(Data!$J$2:$J$16716,Data!$C$2:$C$16716,F18,Data!$P$2:$P$16716,1) -> 88.11 | P18: SNES | Q18: =SUMIFS(Data!$J$2:$J$16716,Data!$B$2:$B$16716,P18,Data!$P$2:$P$16716,1) -> 200.05 | R18: =Q18+ROW()*0.000000001 -> 200.05 | X18: Disney Interactive Studios | Y18: =SUMIFS(Data!$J$2:$J$16716,Data!$E$2:$E$16716,X18,Data!$P$2:$P$16716,1) -> 117.37 | Z18: =Y18+ROW()*0.000000001 -> 117.37
F19: 1996 | G19: =COUNTIFS(Data!$C$2:$C$16716,F19,Data!$P$2:$P$16716,1) -> 263 | H19: =SUMIFS(Data!$J$2:$J$16716,Data!$C$2:$C$16716,F19,Data!$P$2:$P$16716,1) -> 199.15 | P19: GC | Q19: =SUMIFS(Data!$J$2:$J$16716,Data!$B$2:$B$16716,P19,Data!$P$2:$P$16716,1) -> 199.36 | R19: =Q19+ROW()*0.000000001 -> 199.36 | X19: Eidos Interactive | Y19: =SUMIFS(Data!$J$2:$J$16716,Data!$E$2:$E$16716,X19,Data!$P$2:$P$16716,1) -> 98.65 | Z19: =Y19+ROW()*0.000000001 -> 98.65
F20: 1997 | G20: =COUNTIFS(Data!$C$2:$C$16716,F20,Data!$P$2:$P$16716,1) -> 289 | H20: =SUMIFS(Data!$J$2:$J$16716,Data!$C$2:$C$16716,F20,Data!$P$2:$P$16716,1) -> 200.98 | P20: XOne | Q20: =SUMIFS(Data!$J$2:$J$16716,Data!$B$2:$B$16716,P20,Data!$P$2:$P$16716,1) -> 159.44 | R20: =Q20+ROW()*0.000000001 -> 159.44 | X20: LucasArts | Y20: =SUMIFS(Data!$J$2:$J$16716,Data!$E$2:$E$16716,X20,Data!$P$2:$P$16716,1) -> 85.83 | Z20: =Y20+ROW()*0.000000001 -> 85.83
F21: 1998 | G21: =COUNTIFS(Data!$C$2:$C$16716,F21,Data!$P$2:$P$16716,1) -> 379 | H21: =SUMIFS(Data!$J$2:$J$16716,Data!$C$2:$C$16716,F21,Data!$P$2:$P$16716,1) -> 256.45 | P21: 2600 | Q21: =SUMIFS(Data!$J$2:$J$16716,Data!$B$2:$B$16716,P21,Data!$P$2:$P$16716,1) -> 97.08 | R21: =Q21+ROW()*0.000000001 -> 97.08 | X21: Bethesda Softworks | Y21: =SUMIFS(Data!$J$2:$J$16716,Data!$E$2:$E$16716,X21,Data!$P$2:$P$16716,1) -> 85.05 | Z21: =Y21+ROW()*0.000000001 -> 85.05
F22: 1999 | G22: =COUNTIFS(Data!$C$2:$C$16716,F22,Data!$P$2:$P$16716,1) -> 338 | H22: =SUMIFS(Data!$J$2:$J$16716,Data!$C$2:$C$16716,F22,Data!$P$2:$P$16716,1) -> 251.25 | P22: WiiU | Q22: =SUMIFS(Data!$J$2:$J$16716,Data!$B$2:$B$16716,P22,Data!$P$2:$P$16716,1) -> 82.16 | R22: =Q22+ROW()*0.000000001 -> 82.16 | X22: Midway Games | Y22: =SUMIFS(Data!$J$2:$J$16716,Data!$E$2:$E$16716,X22,Data!$P$2:$P$16716,1) -> 69.67 | Z22: =Y22+ROW()*0.000000001 -> 69.67
F23: 2000 | G23: =COUNTIFS(Data!$C$2:$C$16716,F23,Data!$P$2:$P$16716,1) -> 350 | H23: =SUMIFS(Data!$J$2:$J$16716,Data!$C$2:$C$16716,F23,Data!$P$2:$P$16716,1) -> 201.58 | P23: PSV | Q23: =SUMIFS(Data!$J$2:$J$16716,Data!$B$2:$B$16716,P23,Data!$P$2:$P$16716,1) -> 54.12 | R23: =Q23+ROW()*0.000000001 -> 54.12 | X23: Acclaim Entertainment | Y23: =SUMIFS(Data!$J$2:$J$16716,Data!$E$2:$E$16716,X23,Data!$P$2:$P$16716,1) -> 64.15 | Z23: =Y23+ROW()*0.000000001 -> 64.15
F24: 2001 | G24: =COUNTIFS(Data!$C$2:$C$16716,F24,Data!$P$2:$P$16716,1) -> 482 | H24: =SUMIFS(Data!$J$2:$J$16716,Data!$C$2:$C$16716,F24,Data!$P$2:$P$16716,1) -> 331.47 | P24: SAT | Q24: =SUMIFS(Data!$J$2:$J$16716,Data!$B$2:$B$16716,P24,Data!$P$2:$P$16716,1) -> 33.59 | R24: =Q24+ROW()*0.000000001 -> 33.59 | X24: Vivendi Games | Y24: =SUMIFS(Data!$J$2:$J$16716,Data!$E$2:$E$16716,X24,Data!$P$2:$P$16716,1) -> 57.94 | Z24: =Y24+ROW()*0.000000001 -> 57.94
F25: 2002 | G25: =COUNTIFS(Data!$C$2:$C$16716,F25,Data!$P$2:$P$16716,1) -> 829 | H25: =SUMIFS(Data!$J$2:$J$16716,Data!$C$2:$C$16716,F25,Data!$P$2:$P$16716,1) -> 395.51 | P25: GEN | Q25: =SUMIFS(Data!$J$2:$J$16716,Data!$B$2:$B$16716,P25,Data!$P$2:$P$16716,1) -> 28.36 | R25: =Q25+ROW()*0.000000001 -> 28.36 | X25: 505 Games | Y25: =SUMIFS(Data!$J$2:$J$16716,Data!$E$2:$E$16716,X25,Data!$P$2:$P$16716,1) -> 55.32 | Z25: =Y25+ROW()*0.000000001 -> 55.32
F26: 2003 | G26: =COUNTIFS(Data!$C$2:$C$16716,F26,Data!$P$2:$P$16716,1) -> 775 | H26: =SUMIFS(Data!$J$2:$J$16716,Data!$C$2:$C$16716,F26,Data!$P$2:$P$16716,1) -> 357.8 | P26: DC | Q26: =SUMIFS(Data!$J$2:$J$16716,Data!$B$2:$B$16716,P26,Data!$P$2:$P$16716,1) -> 15.97 | R26: =Q26+ROW()*0.000000001 -> 15.97 | X26: Tecmo Koei | Y26: =SUMIFS(Data!$J$2:$J$16716,Data!$E$2:$E$16716,X26,Data!$P$2:$P$16716,1) -> 53.54 | Z26: =Y26+ROW()*0.000000001 -> 53.54
... F33: 2010 | G33: =COUNTIFS(Data!$C$2:$C$16716,F33,Data!$P$2:$P$16716,1) -> 1255 | H33: =SUMIFS(Data!$J$2:$J$16716,Data!$C$2:$C$16716,F33,Data!$P$2:$P$16716,1) -> 590.59 | P33: PCFX | Q33: =SUMIFS(Data!$J$2:$J$16716,Data!$B$2:$B$16716,P33,Data!$P$2:$P$16716,1) -> 0.03 | R33: =Q33+ROW()*0.000000001 -> 0.030000033 | X33: D3Publisher | Y33: =SUMIFS(Data!$J$2:$J$16716,Data!$E$2:$E$16716,X33,Data!$P$2:$P$16716,1) -> 23.74 | Z33: =Y33+ROW()*0.000000001 -> 23.74
F34: 2011 | G34: =COUNTIFS(Data!$C$2:$C$16716,F34,Data!$P$2:$P$16716,1) -> 1136 | H34: =SUMIFS(Data!$J$2:$J$16716,Data!$C$2:$C$16716,F34,Data!$P$2:$P$16716,1) -> 507.79 | X34: Hudson Soft | Y34: =SUMIFS(Data!$J$2:$J$16716,Data!$E$2:$E$16716,X34,Data!$P$2:$P$16716,1) -> 22.94 | Z34: =Y34+ROW()*0.000000001 -> 22.94
F35: 2012 | G35: =COUNTIFS(Data!$C$2:$C$16716,F35,Data!$P$2:$P$16716,1) -> 652 | H35: =SUMIFS(Data!$J$2:$J$16716,Data!$C$2:$C$16716,F35,Data!$P$2:$P$16716,1) -> 355.84 | X35: MTV Games | Y35: =SUMIFS(Data!$J$2:$J$16716,Data!$E$2:$E$16716,X35,Data!$P$2:$P$16716,1) -> 20.72 | Z35: =Y35+ROW()*0.000000001 -> 20.72
F36: 2013 | G36: =COUNTIFS(Data!$C$2:$C$16716,F36,Data!$P$2:$P$16716,1) -> 544 | H36: =SUMIFS(Data!$J$2:$J$16716,Data!$C$2:$C$16716,F36,Data!$P$2:$P$16716,1) -> 361.24 | X36: Universal Interactive | Y36: =SUMIFS(Data!$J$2:$J$16716,Data!$E$2:$E$16716,X36,Data!$P$2:$P$16716,1) -> 17.77 | Z36: =Y36+ROW()*0.000000001 -> 17.77
F37: 2014 | G37: =COUNTIFS(Data!$C$2:$C$16716,F37,Data!$P$2:$P$16716,1) -> 581 | H37: =SUMIFS(Data!$J$2:$J$16716,Data!$C$2:$C$16716,F37,Data!$P$2:$P$16716,1) -> 331.51 | X37: Banpresto | Y37: =SUMIFS(Data!$J$2:$J$16716,Data!$E$2:$E$16716,X37,Data!$P$2:$P$16716,1) -> 17.4 | Z37: =Y37+ROW()*0.000000001 -> 17.4
F38: 2015 | G38: =COUNTIFS(Data!$C$2:$C$16716,F38,Data!$P$2:$P$16716,1) -> 606 | H38: =SUMIFS(Data!$J$2:$J$16716,Data!$C$2:$C$16716,F38,Data!$P$2:$P$16716,1) -> 268.05 | X38: Rising Star Games | Y38: =SUMIFS(Data!$J$2:$J$16716,Data!$E$2:$E$16716,X38,Data!$P$2:$P$16716,1) -> 16.82 | Z38: =Y38+ROW()*0.000000001 -> 16.82
F39: 2016 | G39: =COUNTIFS(Data!$C$2:$C$16716,F39,Data!$P$2:$P$16716,1) -> 502 | H39: =SUMIFS(Data!$J$2:$J$16716,Data!$C$2:$C$16716,F39,Data!$P$2:$P$16716,1) -> 130.1 | X39: Infogrames | Y39: =SUMIFS(Data!$J$2:$J$16716,Data!$E$2:$E$16716,X39,Data!$P$2:$P$16716,1) -> 16.34 | Z39: =Y39+ROW()*0.000000001 -> 16.34
X40: Majesco Entertainment | Y40: =SUMIFS(Data!$J$2:$J$16716,Data!$E$2:$E$16716,X40,Data!$P$2:$P$16716,1) -> 15.79 | Z40: =Y40+ROW()*0.000000001 -> 15.79
X41: Hasbro Interactive | Y41: =SUMIFS(Data!$J$2:$J$16716,Data!$E$2:$E$16716,X41,Data!$P$2:$P$16716,1) -> 15.22 | Z41: =Y41+ROW()*0.000000001 -> 15.22
X42: Nippon Ichi Software | Y42: =SUMIFS(Data!$J$2:$J$16716,Data!$E$2:$E$16716,X42,Data!$P$2:$P$16716,1) -> 13.66 | Z42: =Y42+ROW()*0.000000001 -> 13.66
X43: 989 Studios | Y43: =SUMIFS(Data!$J$2:$J$16716,Data!$E$2:$E$16716,X43,Data!$P$2:$P$16716,1) -> 13.32 | Z43: =Y43+ROW()*0.000000001 -> 13.32
X44: Zoo Digital Publishing | Y44: =SUMIFS(Data!$J$2:$J$16716,Data!$E$2:$E$16716,X44,Data!$P$2:$P$16716,1) -> 12.81 | Z44: =Y44+ROW()*0.000000001 -> 12.81
X45: Atlus | Y45: =SUMIFS(Data!$J$2:$J$16716,Data!$E$2:$E$16716,X45,Data!$P$2:$P$16716,1) -> 12.36 | Z45: =Y45+ROW()*0.000000001 -> 12.36
X46: Level 5 | Y46: =SUMIFS(Data!$J$2:$J$16716,Data!$E$2:$E$16716,X46,Data!$P$2:$P$16716,1) -> 12.24 | Z46: =Y46+ROW()*0.000000001 -> 12.24
X47: Empire Interactive | Y47: =SUMIFS(Data!$J$2:$J$16716,Data!$E$2:$E$16716,X47,Data!$P$2:$P$16716,1) -> 11.29 | Z47: =Y47+ROW()*0.000000001 -> 11.29
X48: ASCII Entertainment | Y48: =SUMIFS(Data!$J$2:$J$16716,Data!$E$2:$E$16716,X48,Data!$P$2:$P$16716,1) -> 10.89 | Z48: =Y48+ROW()*0.000000001 -> 10.89
X49: 3DO | Y49: =SUMIFS(Data!$J$2:$J$16716,Data!$E$2:$E$16716,X49,Data!$P$2:$P$16716,1) -> 10.12 | Z49: =Y49+ROW()*0.000000001 -> 10.12
X50: Crave Entertainment | Y50: =SUMIFS(Data!$J$2:$J$16716,Data!$E$2:$E$16716,X50,Data!$P$2:$P$16716,1) -> 9.86 | Z50: =Y50+ROW()*0.000000001 -> 9.8600001
X51: RedOctane | Y51: =SUMIFS(Data!$J$2:$J$16716,Data!$E$2:$E$16716,X51,Data!$P$2:$P$16716,1) -> 8.68 | Z51: =Y51+ROW()*0.000000001 -> 8.6800001
... X574: UIG Entertainment | Y574: =SUMIFS(Data!$J$2:$J$16716,Data!$E$2:$E$16716,X574,Data!$P$2:$P$16716,1) -> 0.01 | Z574: =Y574+ROW()*0.000000001 -> 0.010000574

Sheet Lists
A1: Genre | B1: Platform Maker | C1: Year
A2: All | B2: All | C2: 1980
A3: Action | B3: Sony | C3: 1981
A4: Sports | B4: Nintendo | C4: 1982
A5: Shooter | B5: Microsoft | C5: 1983
A6: Role-Playing | B6: Sega | C6: 1984
A7: Platform | B7: PC | C7: 1985
A8: Misc | B8: Other | C8: 1986
A9: Racing | C9: 1987
A10: Fighting | C10: 1988
A11: Simulation | C11: 1989
A12: Puzzle | C12: 1990
A13: Adventure | C13: 1991
A14: Strategy | C14: 1992
C15: 1993
C16: 1994
C17: 1995
C18: 1996
C19: 1997
C20: 1998
C21: 1999
C22: 2000
C23: 2001
C24: 2002
C25: 2003
C26: 2004
... C38: 2016

Sheet Insights
B1: Key insights & recommendations (full dataset, no filters)
B3: Market size | C3: 16,715 cleaned release records, 8.92B units sold (1980-2016). Peak year 2008 (672M units).
B4: Hit-driven market | C4: Top 1% of releases = 21% of units; top 10% = 59%; 35% of releases sold under 100k units.
B5: Genres | C5: Action (19.6%), Sports (14.9%), Shooter (11.8%) lead in volume. Platform (0.93M), Shooter (0.80M), RPG (0.62M) earn most per release; Adventure only 0.18M.
B6: Platforms | C6: PS2 #1 (1,256M), then X360, PS3, Wii. Sony 3.59B and Nintendo 3.50B vs Microsoft 1.39B. Each platform has a ~5-8 year sales window.
B7: Publishers | C7: Top 10 hold ~71% of units. Nintendo #1 (1.79B) with 2.5M units per release vs 0.7-0.9M for EA / Activision / Sony.
B8: Best sellers | C8: Wii Sports 82.5M. Combined across platforms GTA V (56.6M) is #2.
B9: Regions | C9: North America 49.4%, Europe 27.2%, Japan 14.6%, Other 8.9%. RPG = 38% Japan; Shooters only 4% Japan.
B10: Ratings vs sales | C10: Critic score vs sales Spearman rho 0.38 (user score 0.16). 90+ rated games average 3.2M units - ~14x games under 50.
B11: Recommend: portfolio | C11: Concentrate on Action / Shooter / RPG / Platform franchises; limit spend on Adventure / Strategy / Puzzle.
B12: Recommend: quality | C12: Invest in QA and polish to reach 80+ critic scores - the largest sales step-up of any factor tested.
B13: Recommend: platforms | C13: Launch early/mid-lifecycle on current-gen platforms and go multi-platform.
B14: Recommend: regions | C14: Lead with NA/EU for shooters, sports, racing; build a Japan-specific plan for RPG and puzzle/strategy.
B15: Limitations | C15: 2016 snapshot, mostly physical retail; no revenue/cost data; ~50% of games unscored; correlation is not causation.

Sheet Cleaning_Log
A1: Step | B1: Rows affected | C1: Note
A2: Raw rows loaded | B2: 16719
A3: Name values with stray whitespace trimmed | B3: 29 | C3: e.g. trailing spaces in Name / Publisher
A4: Rows dropped: missing Name AND Genre | B4: 2 | C4: Both are Genesis 1993 rows, cannot be identified
A5: Invalid Year set to NaN (>2016) | B5: 4 | C5: Impossible for a Dec-2016 snapshot (2017 / 2020 values)
A6: Duplicate Name+Platform rows merged (sales summed) | B6: 2 | C6: 2 games; kept distinct releases with different years
A7: Missing Publisher -> "Unknown" | B7: 53
A8: Missing Developer -> "Unknown" | B8: 6621
A9: Publisher variants consolidated | B9: 9 | C9: Square/SquareSoft->Square Enix, Sony CE America/Europe->Sony CE, etc.
A10: Rating: K-A merged into E; RP set to NaN | B10: 6
A11: Score columns left missing (NOT imputed) | B11: 8580 | C11: Imputing would invent ratings; score analysis uses only rated games
A12: Rows where regions != Global by >0.05M | B12: 0 | C12: Differences <=0.02M are rounding; Global kept as reported
A13: Final rows | B13: 16715 | C13: 4 rows removed in total
